<?xml version="1.0" encoding="ISO-8859-1"?>
<StudyForm>
  <Form FormId="948" FormName="FORM948" FormTitle="Vasospasms">
    <Page PageTitle="Autogenerated*">
      <Item ItemId="2070" ItemType="2" VarName="VAR2070" LoincScale="ORD">
        <FormItem ItemText="Clinical vasospasm?" ItemHelp="" ExcludeFromText="0" ExcludeCaption="0" Visibility="1" CarryForward="1" ReadOnly="0" Optional="0">
          <Answer AnswerId="11033" OrderNumber="1" OptionText="Yes" Score="1.00"/>
          <Answer AnswerId="11034" OrderNumber="2" OptionText="No" Score="2.00"/>
        </FormItem>
      </Item>
      <Item ItemId="2071" ItemType="2" VarName="VAR2071" LoincScale="ORD">
        <FormItem ItemText="Sonographic vasospasm" ItemHelp="" ExcludeFromText="0" ExcludeCaption="0" Visibility="1" CarryForward="0" ReadOnly="0" Optional="1">
          <Answer AnswerId="11035" OrderNumber="1" OptionText="Yes" Score="1.00"/>
          <Answer AnswerId="11036" OrderNumber="2" OptionText="No" Score="2.00"/>
        </FormItem>
      </Item>
    </Page>
  </Form>
  <Actions>
	</Actions>
</StudyForm>
