<?xml version="1.0"?>
<StudyForm>
  <Form FormId="695" FormName="FORM695" FormTitle="Insulinpenndosering">
    <Page PageTitle="Basalinsulin">
      <Item ItemId="3209" ItemType="2" VarName="INS_BASAL_YN" LoincScale="ORD" DisplayFormat="">
        <FormItem ItemText="Bruker basalinsulin" ItemHelp="" MinExpression="" MaxExpression="" ExcludeFromText="0" ExcludeCaption="0" Visibility="1" CarryForward="1" ReadOnly="0" Optional="0">
          <Answer AnswerId="16014" OrderNumber="1" OptionText="Ja" ShortCode="J"/>
          <Answer AnswerId="16015" OrderNumber="2" OptionText="Nei" ShortCode="N"/>
        </FormItem>
      </Item>
    </Page>
    <Page PageTitle="Detaljer basainsulin*">
      <Item ItemId="4214" ItemType="4" VarName="INS_BASAL_NAME" LoincScale="NAR" DisplayFormat="" Multiline="0">
        <FormItem ItemHeader="Preparat" ItemText="Preparatnavn og type penn" ItemHelp="F.eks: Humulin engangspenn, Insulatard Penfill, Lantus SoloStar, Levemir FlexPen" MinExpression="" MaxExpression="" ExcludeFromText="0" ExcludeCaption="0" Visibility="1" CarryForward="1" ReadOnly="0" Optional="0">
          <Answer/>
        </FormItem>
      </Item>
      <Item ItemId="3207" ItemType="1" VarName="INS_BASAL_MORNING" LoincScale="QN" UnitStr="E" DisplayFormat="">
        <FormItem ItemText="Morgen" ItemHelp="" MinExpression="0" MaxExpression="300" ExcludeFromText="0" ExcludeCaption="0" Visibility="1" CarryForward="1" ReadOnly="0" Optional="0" Decimals="1">
          <Answer/>
        </FormItem>
      </Item>
      <Item ItemId="3208" ItemType="1" VarName="INS_BASAL_NOON" LoincScale="QN" UnitStr="E" DisplayFormat="">
        <FormItem ItemText="Middag" ItemHelp="" MinExpression="0" MaxExpression="300" ExcludeFromText="0" ExcludeCaption="0" Visibility="1" CarryForward="1" ReadOnly="0" Optional="0" Decimals="1">
          <Answer/>
        </FormItem>
      </Item>
      <Item ItemId="3210" ItemType="1" VarName="INS_BASAL_EVENING" LoincScale="QN" UnitStr="E" DisplayFormat="">
        <FormItem ItemText="Kveld" ItemHelp="" MinExpression="0" MaxExpression="300" ExcludeFromText="0" ExcludeCaption="0" Visibility="1" CarryForward="1" ReadOnly="0" Optional="0" Decimals="1">
          <Answer/>
        </FormItem>
      </Item>
      <Item ItemId="3906" ItemType="1" VarName="INS_BASAL_SUM" LoincScale="QN" UnitStr="E" DisplayFormat="">
        <FormItem ItemText="Sum basalinsulin" ItemHelp="" Expression="IS0(INS_BASAL_YN-1) * ( INS_BASAL_MORNING*ISPOS(INS_BASAL_MORNING+1) + INS_BASAL_NOON*ISPOS(INS_BASAL_NOON+1)+ INS_BASAL_EVENING *ISPOS(INS_BASAL_EVENING+1))" MinExpression="" MaxExpression="" ExcludeFromText="0" ExcludeCaption="0" Visibility="1" CarryForward="0" ReadOnly="1" Optional="1" Decimals="1">
          <Answer/>
        </FormItem>
      </Item>
    </Page>
    <Page PageTitle="Måltidsinsulin">
      <Item ItemId="3206" ItemType="2" VarName="INS_MEAL_YN" LoincScale="ORD" DisplayFormat="">
        <FormItem ItemText="Bruker måltids-/korreksjonsinsulin" ItemHelp="" MinExpression="" MaxExpression="" ExcludeFromText="0" ExcludeCaption="0" Visibility="1" CarryForward="1" ReadOnly="0" Optional="0">
          <Answer AnswerId="16010" OrderNumber="1" OptionText="Ja" ShortCode="J"/>
          <Answer AnswerId="16011" OrderNumber="2" OptionText="Nei" ShortCode="N"/>
        </FormItem>
      </Item>
    </Page>
    <Page PageTitle="Detaljer måltidsinsulin*">
      <Item ItemId="4215" ItemType="4" VarName="INS_MEAL_NAME" LoincScale="NAR" DisplayFormat="" Multiline="0">
        <FormItem ItemHeader="Preparat*" ItemText="Preparatnavn og type penn" ItemHelp="F.eks: Humalog engangspenn, NovoRapid Flexpen, Actrapid Penfill, Apidra SoloStar, Insuman Rapid" MinExpression="" MaxExpression="" ExcludeFromText="0" ExcludeCaption="0" Visibility="1" CarryForward="1" ReadOnly="0" Optional="0">
          <Answer/>
        </FormItem>
      </Item>
      <Item ItemId="3228" ItemType="1" VarName="INS_MEAL_BREAKFAST" LoincScale="QN" UnitStr="E" DisplayFormat="">
        <FormItem ItemText="Frokost" ItemHelp="" MinExpression="0" MaxExpression="200" ExcludeFromText="0" ExcludeCaption="0" Visibility="1" CarryForward="1" ReadOnly="0" Optional="0" Decimals="1">
          <Answer/>
        </FormItem>
      </Item>
      <Item ItemId="3202" ItemType="1" VarName="INS_MEAL_BRUNCH" LoincScale="QN" UnitStr="E" DisplayFormat="">
        <FormItem ItemText="Brunch" ItemHelp="Mellom frokost og lunsj" MinExpression="0" MaxExpression="200" ExcludeFromText="0" ExcludeCaption="0" Visibility="1" CarryForward="1" ReadOnly="0" Optional="0" Decimals="1">
          <Answer/>
        </FormItem>
      </Item>
      <Item ItemId="3204" ItemType="1" VarName="INS_MEAL_DINNER" LoincScale="QN" UnitStr="E" DisplayFormat="">
        <FormItem ItemText="Middag" ItemHelp="" MinExpression="0" MaxExpression="200" ExcludeFromText="0" ExcludeCaption="0" Visibility="1" CarryForward="1" ReadOnly="0" Optional="0" Decimals="1">
          <Answer/>
        </FormItem>
      </Item>
      <Item ItemId="3200" ItemType="1" VarName="INS_MEAL_SUPPER" LoincScale="QN" UnitStr="E" DisplayFormat="">
        <FormItem ItemText="Kvelds" ItemHelp="" MinExpression="0" MaxExpression="200" ExcludeFromText="0" ExcludeCaption="0" Visibility="1" CarryForward="1" ReadOnly="0" Optional="0" Decimals="1">
          <Answer/>
        </FormItem>
      </Item>
      <Item ItemId="3905" ItemType="1" VarName="INS_MEAL_SUM" LoincScale="QN" UnitStr="E" DisplayFormat="">
        <FormItem ItemText="Sum måltids-/korreksjonsinsulin" ItemHelp="" Expression="IS0(INS_MEAL_YN-1) * ( INS_MEAL_BREAKFAST*ISPOS(INS_MEAL_BREAKFAST+1) + INS_MEAL_BRUNCH*ISPOS(INS_MEAL_BRUNCH+1) + INS_MEAL_LUNCH*ISPOS(INS_MEAL_LUNCH+1) + INS_MEAL_DINNER*ISPOS(INS_MEAL_DINNER+1) + INS_MEAL_SUPPER*ISPOS(INS_MEAL_SUPPER+1) )" MinExpression="" MaxExpression="" ExcludeFromText="0" ExcludeCaption="0" Visibility="1" CarryForward="0" ReadOnly="1" Optional="1" Decimals="1">
          <Answer/>
        </FormItem>
      </Item>
    </Page>
    <Page PageTitle="Premix-insulin">
      <Item ItemId="3201" ItemType="2" VarName="INS_PREMIX_YN" LoincScale="ORD" DisplayFormat="">
        <FormItem ItemText="Bruker premix-insulin" ItemHelp="" MinExpression="" MaxExpression="" ExcludeFromText="0" ExcludeCaption="0" Visibility="1" CarryForward="1" ReadOnly="0" Optional="0">
          <Answer AnswerId="16006" OrderNumber="1" OptionText="Ja" ShortCode="J"/>
          <Answer AnswerId="16007" OrderNumber="2" OptionText="Nei" ShortCode="N"/>
        </FormItem>
      </Item>
    </Page>
    <Page PageTitle="Detaljer premix-insulin*">
      <Item ItemId="4216" ItemType="4" VarName="INS_PREMIX_NAME" LoincScale="NAR" DisplayFormat="" Multiline="0">
        <FormItem ItemHeader="Preparat*" ItemText="Preparatnavn og type penn" ItemHelp="F.eks: Humalog Mix25 engangspenn, NovoMix 30 FlexPen, Insuman Comb 25 OptiSet" MinExpression="" MaxExpression="" ExcludeFromText="0" ExcludeCaption="0" Visibility="1" CarryForward="1" ReadOnly="0" Optional="0">
          <Answer/>
        </FormItem>
      </Item>
      <Item ItemId="3221" ItemType="1" VarName="INS_PREMIX_MORNING" LoincScale="QN" UnitStr="E" DisplayFormat="">
        <FormItem ItemText="Morgen" ItemHelp="" MinExpression="0" MaxExpression="300" ExcludeFromText="0" ExcludeCaption="0" Visibility="1" CarryForward="1" ReadOnly="0" Optional="0" Decimals="1">
          <Answer/>
        </FormItem>
      </Item>
      <Item ItemId="3904" ItemType="1" VarName="INS_PREMIX_NOON" LoincScale="QN" UnitStr="E" DisplayFormat="">
        <FormItem ItemText="Midt på dagen" ItemHelp="" MinExpression="0" MaxExpression="300" ExcludeFromText="0" ExcludeCaption="0" Visibility="1" CarryForward="1" ReadOnly="0" Optional="0" Decimals="1">
          <Answer/>
        </FormItem>
      </Item>
      <Item ItemId="3205" ItemType="1" VarName="INS_PREMIX_EVENING" LoincScale="QN" UnitStr="E" DisplayFormat="">
        <FormItem ItemText="Kveld" ItemHelp="" MinExpression="0" MaxExpression="300" ExcludeFromText="0" ExcludeCaption="0" Visibility="1" CarryForward="1" ReadOnly="0" Optional="0" Decimals="1">
          <Answer/>
        </FormItem>
      </Item>
      <Item ItemId="3907" ItemType="1" VarName="INS_PREMIX_SUM" LoincScale="QN" UnitStr="E" DisplayFormat="">
        <FormItem ItemText="Sum premix-insulin" ItemHelp="" Expression="IS0(INS_PREMIX_YN-1) * ( INS_PREMIX_MORNING*ISPOS(INS_PREMIX_MORNING+1) + INS_PREMIX_NOON*ISPOS(INS_PREMIX_NOON+1) + INS_PREMIX_EVENING*ISPOS(INS_PREMIX_EVENING+1) )" MinExpression="" MaxExpression="" ExcludeFromText="0" ExcludeCaption="0" Visibility="1" CarryForward="0" ReadOnly="1" Optional="1" Decimals="1">
          <Answer/>
        </FormItem>
      </Item>
    </Page>
    <Page PageTitle="Totalsum" PageIntroduction="Inkluderer bare dosering i dette skjemaet, ikke evt. pumpe.">
      <Item ItemId="3908" ItemType="1" VarName="INS_ALL_SUM" LoincScale="QN" UnitStr="E" DisplayFormat="">
        <FormItem ItemText="Døgndose" ItemHelp="" Expression="INS_MEAL_SUM + INS_BASAL_SUM + INS_PREMIX_SUM" MinExpression="" MaxExpression="" ExcludeFromText="0" ExcludeCaption="0" Visibility="1" CarryForward="0" ReadOnly="1" Optional="1" Decimals="1">
          <Answer/>
        </FormItem>
      </Item>
    </Page>
  </Form>
  <Actions>
    <PageAction MasterId="3209">
      <Activate EnumVal="1" PageConditionId="5588" PageNumber="2" ComparisonType="1" ComparisonDescription="Equal to"/>
    </PageAction>
  </Actions>
</StudyForm>
