<?xml version="1.0" encoding="ISO-8859-1"?>
<StudyForm>
  <Form FormId="520" FormName="DIAPOL_FOOT" FormTitle="Fotstatus" Copyright="Norsk Diabetesregister for voskne">
    <Page PageTitle="Fotstatus">
      <Item ItemId="4618" ItemType="5" VarName="DIAPOL_FOOT_REFDATE" LoincScale="DATE" DisplayFormat="">
        <FormItem ItemText="Første gang henvist til fotteam" ItemHelp="Dato for første henvisning" MinExpression="" MaxExpression="" ExcludeFromText="0" ExcludeCaption="0" Visibility="1" CarryForward="1" Optional="1">
          <Answer/>
        </FormItem>
      </Item>
      <Item ItemId="4619" ItemType="4" VarName="DIAPOL_FOOT_PROBLEM" LoincScale="NAR" DisplayFormat="" Multiline="1">
        <FormItem ItemText="Dagens problemstilling" ItemHelp="" MinExpression="" MaxExpression="" ExcludeFromText="0" ExcludeCaption="0" Visibility="1" CarryForward="1" Optional="1">
          <Answer/>
        </FormItem>
      </Item>
      <Item ItemId="6384" ItemType="1" VarName="VMR_LAB_HBA1C" LoincScale="QN" UnitStr="%" DisplayFormat="">
        <FormItem ItemText="Siste HbA1c (%)" ItemHelp="Hentes inn automatisk fra labarket, kan ikke redigeres her." Expression="LabData.HbA1c" MinExpression="3" MaxExpression="15" ExcludeFromText="1" ExcludeCaption="0" Visibility="1" CarryForward="0" ReadOnly="1" Optional="1" Decimals="1">
          <Answer/>
        </FormItem>
      </Item>
      <Item ItemId="6382" ItemType="2" VarName="VAR6382" LoincScale="ORD" DisplayFormat="">
        <FormItem ItemHeader="Følges opp av" ItemText="Hvem følger opp fotstatus hos pasienten?" ItemHelp="" MinExpression="" MaxExpression="" ExcludeFromText="0" ExcludeCaption="0" Visibility="1" CarryForward="1" Optional="0">
          <Answer AnswerId="33797" OrderNumber="1" OptionText="Ingen" VerboseText="Ingen fast fot-oppfølging."/>
          <Answer AnswerId="33798" OrderNumber="2" OptionText="Fotterapeut her" VerboseText="Fotstatus følges opp av fotterapeut her."/>
          <Answer AnswerId="33799" OrderNumber="3" OptionText="Fotterapeut i PHT" VerboseText="Følges opp av fotterapeut i PHT."/>
          <Answer AnswerId="33803" OrderNumber="4" OptionText="Andre" VerboseText="Følges opp av andre."/>
        </FormItem>
      </Item>
      <Item ItemId="3248" ItemType="2" VarName="DIAPOL_FOOT_DEFORMITY" LoincScale="ORD" DisplayFormat="Vertical">
        <FormItem ItemText="Fotdeformiteter" ItemHelp="Hallux valgus, hammertå, charcot" MinExpression="" MaxExpression="" ExcludeFromText="0" ExcludeCaption="0" Visibility="1" CarryForward="1" Optional="0">
          <Answer AnswerId="16210" OrderNumber="1" OptionText="Ingen fotdeformitet." ShortCode="N"/>
          <Answer AnswerId="16211" OrderNumber="2" OptionText="Fotdeformitet venstre side." ShortCode="V"/>
          <Answer AnswerId="16216" OrderNumber="3" OptionText="Fotdeformitet høyre side." ShortCode="H"/>
          <Answer AnswerId="16217" OrderNumber="4" OptionText="Bilaterale fotdeformiteter." ShortCode="B"/>
        </FormItem>
      </Item>
    </Page>
    <Page PageTitle="Beskrivelse av fotdeformitet*">
      <Item ItemId="6383" ItemType="4" VarName="VAR6383" LoincScale="NAR" DisplayFormat="" Multiline="1">
        <FormItem ItemText="Beskrivelse" ItemHelp="" MinExpression="" MaxExpression="" ExcludeFromText="0" ExcludeCaption="0" Visibility="1" CarryForward="0" Optional="1">
          <Answer/>
        </FormItem>
      </Item>
    </Page>
    <Page PageTitle="Spesialundersøkelser">
      <Item ItemId="4620" ItemType="5" VarName="DIAPOL_VASCSURG_REFDATE" LoincScale="DATE" DisplayFormat="">
        <FormItem ItemText="Henvist karkirurg" ItemHelp="Beste estimat ved usikker dato." MinExpression="DOB" MaxExpression="NOW" ExcludeFromText="0" ExcludeCaption="0" Visibility="1" CarryForward="1" Optional="1">
          <Answer/>
        </FormItem>
      </Item>
      <Item ItemId="3259" ItemType="5" VarName="DIAPOL_VASCSURGEXAM_DATE" LoincScale="DATE" DisplayFormat="">
        <FormItem ItemHeader="Vurdert av karkirurg" ItemText="Siste karkirurgiske vurdering av føttene" ItemHelp="Beste estimat ved usikker dato." MinExpression="DOB" MaxExpression="NOW" ExcludeFromText="0" ExcludeCaption="0" Visibility="1" CarryForward="1" Optional="1">
          <Answer/>
        </FormItem>
      </Item>
      <Item ItemId="6386" ItemType="4" VarName="VAR6386" LoincScale="NAR" DisplayFormat="" Multiline="1">
        <FormItem ItemText="Kommentar" ItemHelp="" MinExpression="" MaxExpression="" ExcludeFromText="0" ExcludeCaption="0" Visibility="1" CarryForward="0" Optional="1">
          <Answer/>
        </FormItem>
      </Item>
      <Item ItemId="4008" ItemType="5" VarName="DIAPOL_ENDOVASC_DATE" LoincScale="DATE" DisplayFormat="">
        <FormItem ItemText="Siste endovaskulære behandling" ItemHelp="Beste estimat ved usikker dato." MinExpression="DOB" MaxExpression="NOW" ExcludeFromText="0" ExcludeCaption="0" Visibility="1" CarryForward="1" Optional="1">
          <Answer/>
        </FormItem>
      </Item>
      <Item ItemId="6388" ItemType="4" VarName="VAR6388" LoincScale="NAR" DisplayFormat="" Multiline="1">
        <FormItem ItemText="Kommentar" ItemHelp="" MinExpression="" MaxExpression="" ExcludeFromText="0" ExcludeCaption="0" Visibility="1" CarryForward="0" Optional="1">
          <Answer/>
        </FormItem>
      </Item>
      <Item ItemId="4009" ItemType="5" VarName="DIAPOL_ANGIOGRAPH_DATE" LoincScale="DATE" DisplayFormat="">
        <FormItem ItemText="Siste angiografi" ItemHelp="Beste estimat ved usikker dato." MinExpression="DOB" MaxExpression="NOW" ExcludeFromText="0" ExcludeCaption="0" Visibility="1" CarryForward="1" Optional="1">
          <Answer/>
        </FormItem>
      </Item>
      <Item ItemId="6389" ItemType="4" VarName="VAR6389" LoincScale="NAR" DisplayFormat="" Multiline="1">
        <FormItem ItemText="Kommentar" ItemHelp="" MinExpression="" MaxExpression="" ExcludeFromText="0" ExcludeCaption="0" Visibility="1" CarryForward="0" Optional="1">
          <Answer/>
        </FormItem>
      </Item>
      <Item ItemId="6385" ItemType="5" VarName="VAR6385" LoincScale="DATE" DisplayFormat="">
        <FormItem ItemHeader="Vurdert av ortoped" ItemText="Siste vurdering av føttene hos ortoped" ItemHelp="Beste estimat ved usikker dato." MinExpression="DOB" MaxExpression="NOW" ExcludeFromText="0" ExcludeCaption="0" Visibility="1" CarryForward="1" Optional="1">
          <Answer/>
        </FormItem>
      </Item>
      <Item ItemId="6390" ItemType="4" VarName="VAR6390" LoincScale="NAR" DisplayFormat="" Multiline="1">
        <FormItem ItemText="Kommentar" ItemHelp="" MinExpression="" MaxExpression="" ExcludeFromText="0" ExcludeCaption="0" Visibility="1" CarryForward="0" Optional="1">
          <Answer/>
        </FormItem>
      </Item>
      <Item ItemId="4621" ItemType="5" VarName="FOOT_MR_REFDATE" LoincScale="DATE" DisplayFormat="">
        <FormItem ItemText="Henvist til MR" ItemHelp="Dato" MinExpression="DOB" MaxExpression="NOW" ExcludeFromText="0" ExcludeCaption="0" Visibility="1" CarryForward="1" Optional="1">
          <Answer/>
        </FormItem>
      </Item>
      <Item ItemId="6391" ItemType="4" VarName="VAR6391" LoincScale="NAR" DisplayFormat="" Multiline="1">
        <FormItem ItemText="Kommentar" ItemHelp="" MinExpression="" MaxExpression="" ExcludeFromText="0" ExcludeCaption="0" Visibility="1" CarryForward="0" Optional="1">
          <Answer/>
        </FormItem>
      </Item>
    </Page>
    <Page PageTitle="Amputasjoner*">
      <Item ItemId="3241" ItemType="5" VarName="DIAPOL_AMPUTATION_DATE" LoincScale="DATE" DisplayFormat="">
        <FormItem ItemHeader="Første amputasjon" ItemText="Første amputasjon i undereks." ItemHelp="Beste estimat ved usikker dato." MinExpression="DOB" MaxExpression="NOW" ExcludeFromText="0" ExcludeCaption="0" Visibility="1" CarryForward="1" Optional="1">
          <Answer/>
        </FormItem>
      </Item>
      <Item ItemId="3262" ItemType="2" VarName="DIAPOL_AMPUT_LEFT" LoincScale="ORD" DisplayFormat="Vertical">
        <FormItem ItemText="Amputert venstre" ItemHelp="" MinExpression="" MaxExpression="" ExcludeFromText="0" ExcludeCaption="0" Visibility="1" CarryForward="1" Optional="0">
          <Answer AnswerId="16258" OrderNumber="1" OptionText="digit/metatars."/>
          <Answer AnswerId="16259" OrderNumber="2" OptionText="forfot."/>
          <Answer AnswerId="16260" OrderNumber="3" OptionText="transtibialt."/>
          <Answer AnswerId="16261" OrderNumber="4" OptionText="transfemoralt."/>
          <Answer AnswerId="16262" OrderNumber="5" OptionText="Ingen amputasjon v.side."/>
        </FormItem>
      </Item>
      <Item ItemId="3261" ItemType="2" VarName="DIAPOL_AMPUT_RIGHT" LoincScale="ORD" DisplayFormat="Vertical">
        <FormItem ItemText="Amputert høyre" ItemHelp="" MinExpression="" MaxExpression="" ExcludeFromText="0" ExcludeCaption="0" Visibility="1" CarryForward="1" Optional="0">
          <Answer AnswerId="16253" OrderNumber="1" OptionText="digit/metatars."/>
          <Answer AnswerId="16254" OrderNumber="2" OptionText="forfot."/>
          <Answer AnswerId="16255" OrderNumber="3" OptionText="transtibialt."/>
          <Answer AnswerId="16256" OrderNumber="4" OptionText="transfemoralt."/>
          <Answer AnswerId="16257" OrderNumber="5" OptionText="Ingen amputasjon h.side."/>
        </FormItem>
      </Item>
    </Page>
    <Page PageTitle="Dagens fotstatus">
      <Item ItemId="3242" ItemType="2" VarName="DIAPOL_FOOTPULSE" LoincScale="ORD" DisplayFormat="Vertical">
        <FormItem ItemText="Fotpuls" ItemHelp="Palpabel a.dorsalis pedis eller a.tibialis anterior" MinExpression="" MaxExpression="" ExcludeFromText="0" ExcludeCaption="0" Visibility="1" CarryForward="1" Optional="1">
          <Answer AnswerId="16190" OrderNumber="1" OptionText="ikke palpabel på noen side."/>
          <Answer AnswerId="16191" OrderNumber="2" OptionText="palpabel bare på venstre side."/>
          <Answer AnswerId="16192" OrderNumber="3" OptionText="palpabel bare på høyre."/>
          <Answer AnswerId="16193" OrderNumber="4" OptionText="palpabel bilateralt."/>
        </FormItem>
      </Item>
      <Item ItemId="3318" ItemType="2" VarName="NDV_FOOTPULSE" LoincScale="ORD" DisplayFormat="Vertical">
        <FormItem ItemHeader="Fotpuls" ItemText="Palpabel puls på fotrygg eller bak med.malleol på begge føtter" ItemHelp="" Expression="2-ISNULL(DIAPOL_FOOTPULSE-4)+ISNULL(DIAPOL_FOOTPULSE+1)" MinExpression="" MaxExpression="" ExcludeFromText="0" ExcludeCaption="0" Visibility="0" CarryForward="0" Optional="1">
          <Answer AnswerId="16401" OrderNumber="1" OptionText="Ja"/>
          <Answer AnswerId="16402" OrderNumber="2" OptionText="Nei" ShortCode="N"/>
          <Answer AnswerId="16403" OrderNumber="3" OptionText="Ikke undersøkt"/>
          <Answer AnswerId="21368" OrderNumber="4" OptionText="Vet ikke"/>
        </FormItem>
      </Item>
      <Item ItemId="3244" ItemType="1" VarName="DIAPOL_MONOFIL_LEFT" LoincScale="QN" UnitStr="av 4" DisplayFormat="">
        <FormItem ItemText="Monofilament V (av 4)" ItemHelp="10g monofilament." MinExpression="0" MaxExpression="4" ExcludeFromText="0" ExcludeCaption="0" Visibility="1" CarryForward="1" Highlight="1" Optional="1">
          <Answer/>
        </FormItem>
      </Item>
      <Item ItemId="3243" ItemType="1" VarName="DIAPOL_MONOFIL_RIGHT" LoincScale="QN" UnitStr="av 4" DisplayFormat="">
        <FormItem ItemText="Monofilament H (av 4)" ItemHelp="10g monofilament." MinExpression="0" MaxExpression="4" ExcludeFromText="0" ExcludeCaption="0" Visibility="1" CarryForward="1" Highlight="1" Optional="1">
          <Answer/>
        </FormItem>
      </Item>
      <Item ItemId="3246" ItemType="2" VarName="DIAPOL_VIBR_LEFT" LoincScale="ORD" DisplayFormat="Vertical">
        <FormItem ItemText="Vibrasjonssans V" ItemHelp="Stemmegaffel 128Hz ved stortåens grunnledd." MinExpression="" MaxExpression="" ExcludeFromText="0" ExcludeCaption="0" Visibility="1" CarryForward="1" Optional="1">
          <Answer AnswerId="16200" OrderNumber="1" OptionText="normal."/>
          <Answer AnswerId="16201" OrderNumber="2" OptionText="svekket."/>
        </FormItem>
      </Item>
      <Item ItemId="3245" ItemType="2" VarName="DIAPOL_VIBR_RIGHT" LoincScale="ORD" DisplayFormat="Vertical">
        <FormItem ItemText="Vibrasjonssans H" ItemHelp="Stemmegaffel 128 Hz ved stortåens grunnledd." MinExpression="" MaxExpression="" ExcludeFromText="0" ExcludeCaption="0" Visibility="1" CarryForward="1" Optional="1">
          <Answer AnswerId="16198" OrderNumber="1" OptionText="normal."/>
          <Answer AnswerId="16199" OrderNumber="2" OptionText="svekket."/>
        </FormItem>
      </Item>
      <Item ItemId="3319" ItemType="2" VarName="NDV_NEUROPATHY" LoincScale="ORD" DisplayFormat="Horizontal">
        <FormItem ItemHeader="Normal sensibilitet i føtter" ItemText="Monofilament 8/8 eller normal vibrasjonssans ved stortåens ytterledd på begge føtter" ItemHelp="Kjenner vibrasjon. Stemmegaffel på 128 Hz eller monofilament 8/8 må brukes (ellers anføres ”ikke undersøkt”).  Det er nok med ett unormalt funn for å svare Nei." Expression="1 + ISNULL( ISNULL( DIAPOL_MONOFIL_LEFT + DIAPOL_MONOFIL_RIGHT - 8 ) + ISNULL( DIAPOL_MONOFIL_LEFT + DIAPOL_MONOFIL_RIGHT + 2 ) + ISNULL( DIAPOL_MONOFIL_LEFT + DIAPOL_MONOFIL_RIGHT - 3 ) + ISPOS( ISNULL(DIAPOL_VIBR_LEFT + DIAPOL_VIBR_RIGHT-2) +  ISNULL(DIAPOL_VIBR_LEFT + DIAPOL_VIBR_RIGHT+2) + ISNULL(DIAPOL_VIBR_LEFT + DIAPOL_VIBR_RIGHT) ) - 2)" MinExpression="" MaxExpression="" ExcludeFromText="0" ExcludeCaption="0" Visibility="0" CarryForward="0" Optional="1">
          <Answer AnswerId="16413" OrderNumber="1" OptionText="Ja"/>
          <Answer AnswerId="16414" OrderNumber="2" OptionText="Nei" VerboseText="Perifer nevropati." ShortCode="N"/>
          <Answer AnswerId="16415" OrderNumber="3" OptionText="Ikke undersøkt"/>
          <Answer AnswerId="21935" OrderNumber="4" OptionText="Vet ikke"/>
        </FormItem>
      </Item>
    </Page>
    <Page PageTitle="Callus*">
      <Item ItemId="3249" ItemType="2" VarName="DIAPOL_CALLUS" LoincScale="ORD" DisplayFormat="">
        <FormItem ItemText="Callus på føttene" ItemHelp="" MinExpression="" MaxExpression="" ExcludeFromText="0" ExcludeCaption="0" Visibility="1" CarryForward="0" Optional="1">
          <Answer AnswerId="16218" OrderNumber="1" OptionText="Ingen callus på noen av føttene." ShortCode="N"/>
          <Answer AnswerId="16219" OrderNumber="2" OptionText="Callus V." ShortCode="V"/>
          <Answer AnswerId="16220" OrderNumber="3" OptionText="Callus H." ShortCode="H"/>
          <Answer AnswerId="16221" OrderNumber="4" OptionText="Callus bilateralt." ShortCode="B"/>
        </FormItem>
      </Item>
    </Page>
    <Page PageTitle="Kommentar callus*">
      <Item ItemId="3273" ItemType="4" VarName="DIAPOL_CALLUS_COMMENT" LoincScale="NAR" DisplayFormat="" Multiline="1">
        <FormItem ItemText="Kommentar callus:" ItemHelp="Gi en kort beskrivelse" MinExpression="" MaxExpression="" ExcludeFromText="0" ExcludeCaption="0" Visibility="1" CarryForward="0" Optional="1">
          <Answer/>
        </FormItem>
      </Item>
    </Page>
    <Page PageTitle="Perifert blodtrykk">
      <Item ItemId="6392" ItemType="2" VarName="VAR6392" LoincScale="ORD" DisplayFormat="">
        <FormItem ItemText="Er det målt ankel/tåtrykk?" ItemHelp="" MinExpression="" MaxExpression="" ExcludeFromText="1" ExcludeCaption="0" Visibility="1" CarryForward="0" Optional="1">
          <Answer AnswerId="33806" OrderNumber="1" OptionText="Ja"/>
          <Answer AnswerId="33807" OrderNumber="2" OptionText="Nei" ShortCode="N"/>
        </FormItem>
      </Item>
    </Page>
    <Page PageTitle="">
      <Item ItemId="1816" ItemType="1" VarName="REFBP" LoincScale="QN" UnitStr="mmHg" DisplayFormat="">
        <FormItem ItemText="Referanseblodtrykk for indekser" ItemHelp="Systolisk blodtrykk målt på armen like før ankeltrykksmåling" MinExpression="50" MaxExpression="300" ExcludeFromText="0" ExcludeCaption="0" Visibility="1" CarryForward="0" Optional="0">
          <Answer/>
        </FormItem>
      </Item>
      <Item ItemId="1817" ItemType="1" VarName="ANKLEPRESSLEFT" LoincScale="QN" UnitStr="mmHg" DisplayFormat="">
        <FormItem ItemText="Ankeltrykk venstre" ItemHelp="" MinExpression="0" MaxExpression="300" ExcludeFromText="0" ExcludeCaption="0" Visibility="1" CarryForward="0" Optional="0">
          <Answer/>
        </FormItem>
      </Item>
      <Item ItemId="1818" ItemType="1" VarName="ANKLEPRESSRIGHT" LoincScale="QN" UnitStr="mmHg" DisplayFormat="">
        <FormItem ItemText="Ankeltrykk høyre" ItemHelp="" MinExpression="0" MaxExpression="300" ExcludeFromText="0" ExcludeCaption="0" Visibility="1" CarryForward="0" Optional="0">
          <Answer/>
        </FormItem>
      </Item>
      <Item ItemId="1819" ItemType="1" VarName="ABILEFT" LoincScale="QN" DisplayFormat="">
        <FormItem ItemText="Ankel-brachial indeks - venstre" ItemHelp="" Expression="ANKLEPRESSLEFT/REFBP" MinExpression="" MaxExpression="" ExcludeFromText="0" ExcludeCaption="0" Visibility="1" CarryForward="0" Optional="1" Decimals="2">
          <Answer/>
        </FormItem>
      </Item>
      <Item ItemId="1820" ItemType="1" VarName="ABIRIGHT" LoincScale="QN" DisplayFormat="">
        <FormItem ItemText="Ankel-brachial indeks - høyre" ItemHelp="" Expression="ANKLEPRESSRIGHT/REFBP" MinExpression="" MaxExpression="" ExcludeFromText="0" ExcludeCaption="0" Visibility="1" CarryForward="0" Optional="1" Decimals="2">
          <Answer/>
        </FormItem>
      </Item>
      <Item ItemId="4006" ItemType="1" VarName="TOEPRESS_LEFT" LoincScale="QN" UnitStr="mmHg" DisplayFormat="">
        <FormItem ItemText="Tåtrykk venstre" ItemHelp="Unngå å blåse opp mansjett til over 200mmHg." MinExpression="0" MaxExpression="250" ExcludeFromText="0" ExcludeCaption="0" Visibility="1" CarryForward="0" Optional="1">
          <Answer/>
        </FormItem>
      </Item>
      <Item ItemId="4007" ItemType="1" VarName="TOEPRESS_RIGHT" LoincScale="QN" UnitStr="mmHg" DisplayFormat="">
        <FormItem ItemText="Tåtrykk høyre" ItemHelp="Unngå å blåse opp mansjett til over 200mmHg." MinExpression="0" MaxExpression="250" ExcludeFromText="0" ExcludeCaption="0" Visibility="1" CarryForward="0" Optional="1">
          <Answer/>
        </FormItem>
      </Item>
    </Page>
    <Page PageTitle="Fotsår">
      <Item ItemId="3218" ItemType="2" VarName="NDV_FOOT_ULCER" LoincScale="ORD" DisplayFormat="">
        <FormItem ItemHeader="Diabetisk fotsår" ItemText="Har noen gang hatt diabetessår nedenfor ankelen?" ItemHelp="" MinExpression="" MaxExpression="" ExcludeFromText="0" ExcludeCaption="0" Visibility="1" CarryForward="1" Highlight="1" Optional="0">
          <Answer AnswerId="16057" OrderNumber="1" OptionText="Nei, aldri" VerboseText="Aldri fotsår." ShortCode="N"/>
          <Answer AnswerId="16058" OrderNumber="2" OptionText="Ja, en gang" VerboseText="Har hatt fotsår før." ShortCode="En"/>
          <Answer AnswerId="21248" OrderNumber="3" OptionText="Ja, flere ganger" VerboseText="Har hatt flere fotsår." ShortCode="Fler"/>
          <Answer AnswerId="22279" OrderNumber="4" OptionText="Vet ikke" ShortCode="U"/>
        </FormItem>
      </Item>
    </Page>
    <Page PageTitle="Aktuelle fotsår*">
      <Item ItemId="3250" ItemType="1" VarName="ULCER_COUNT" LoincScale="QN" DisplayFormat="">
        <FormItem ItemText="Antall aktuelle fotsår" ItemHelp="Du kan registrere detaljer om inntil 3 fotsår.  Start med det viktigste." MinExpression="0" MaxExpression="6" ExcludeFromText="0" ExcludeCaption="0" Visibility="1" CarryForward="0" Optional="0">
          <Answer/>
        </FormItem>
      </Item>
    </Page>
    <Page PageTitle="Fotsår tilstede*" PageIntroduction="Denne siden er skjult">
      <Item ItemId="4282" ItemType="2" VarName="ULCER_YN" LoincScale="ORD" DisplayFormat="Horizontal">
        <FormItem ItemText="Fotsår tilstede" ItemHelp="Skjult avledet variabel" Expression="2-ISPOS(ULCER_COUNT)" MinExpression="" MaxExpression="" ExcludeFromText="0" ExcludeCaption="0" Visibility="0" CarryForward="0" Optional="1">
          <Answer AnswerId="22958" OrderNumber="1" OptionText="Ja"/>
          <Answer AnswerId="22959" OrderNumber="2" OptionText="Nei" ShortCode="N"/>
        </FormItem>
      </Item>
      <Item ItemId="10316" ItemType="2" VarName="tmpUlcerCount" LoincScale="ORD" DisplayFormat="">
        <FormItem ItemText="Antall fotsår" ItemHelp="" Expression="ISPOS(ULCER_COUNT) + ISPOS(ULCER_COUNT-1) + ISPOS(ULCER_COUNT-2)" ExcludeFromText="0" ExcludeCaption="0" Visibility="-1" CarryForward="0" ReadOnly="0" Optional="1">
          <Answer AnswerId="57849" OrderNumber="1" OptionText="Ett"/>
          <Answer AnswerId="57850" OrderNumber="2" OptionText="To"/>
          <Answer AnswerId="57851" OrderNumber="3" OptionText="Tre eller flere"/>
        </FormItem>
      </Item>
    </Page>
    <Page PageTitle="Antibiotikabehandling">
      <Item ItemId="4263" ItemType="5" VarName="ULCER_AB_DATE" LoincScale="DATE" DisplayFormat="">
        <FormItem ItemText="Startdato for kur" ItemHelp="" MinExpression="DOB" MaxExpression="NOW" ExcludeFromText="0" ExcludeCaption="0" Visibility="1" CarryForward="1" Optional="1">
          <Answer/>
        </FormItem>
      </Item>
      <Item ItemId="4264" ItemType="4" VarName="ULCER_AB_DRUG" LoincScale="NAR" DisplayFormat="" Multiline="0">
        <FormItem ItemText="Preparat og dosering" ItemHelp="" MinExpression="" MaxExpression="" ExcludeFromText="0" ExcludeCaption="0" Visibility="1" CarryForward="1" Optional="1">
          <Answer/>
        </FormItem>
      </Item>
      <Item ItemId="4628" ItemType="5" VarName="ULCER_AB_STOP" LoincScale="DATE" DisplayFormat="">
        <FormItem ItemText="Sluttdato for kur" ItemHelp="" MinExpression="" MaxExpression="" ExcludeFromText="0" ExcludeCaption="0" Visibility="1" CarryForward="1" Optional="1">
          <Answer/>
        </FormItem>
      </Item>
    </Page>
    <Page PageTitle="Sår 1">
      <Item ItemId="3253" ItemType="2" VarName="ULCER1_LATERALITY" LoincScale="ORD" DisplayFormat="">
        <FormItem ItemText="Side" ItemHelp="" MinExpression="" MaxExpression="" ExcludeFromText="0" ExcludeCaption="0" Visibility="1" CarryForward="1" Optional="0">
          <Answer AnswerId="16241" OrderNumber="1" OptionText="Venstre side."/>
          <Answer AnswerId="16242" OrderNumber="2" OptionText="Høyre side."/>
        </FormItem>
      </Item>
      <Item ItemId="4011" ItemType="2" VarName="ULCER1_LOCATION" LoincScale="ORD" DisplayFormat="">
        <FormItem ItemText="Lokalisasjon" ItemHelp="" MinExpression="" MaxExpression="" ExcludeFromText="0" ExcludeCaption="0" Visibility="1" CarryForward="1" Optional="0">
          <Answer AnswerId="20909" OrderNumber="1" OptionText="Stortå"/>
          <Answer AnswerId="20910" OrderNumber="2" OptionText="Andre tær*"/>
          <Answer AnswerId="20911" OrderNumber="3" OptionText="Metatars"/>
          <Answer AnswerId="20912" OrderNumber="4" OptionText="Hæl"/>
          <Answer AnswerId="20913" OrderNumber="5" OptionText="Annen*"/>
        </FormItem>
      </Item>
      <Item ItemId="3269" ItemType="5" VarName="ULCER1_SINCE" LoincScale="DATE" DisplayFormat="">
        <FormItem ItemText="Hatt siden" ItemHelp="" MinExpression="" MaxExpression="" ExcludeFromText="0" ExcludeCaption="0" Visibility="1" CarryForward="1" Optional="0">
          <Answer/>
        </FormItem>
      </Item>
      <Item ItemId="4016" ItemType="2" VarName="ULCER1_DEPTH" LoincScale="ORD" DisplayFormat="Vertical">
        <FormItem ItemText="Dybde" ItemHelp="" MinExpression="" MaxExpression="" ExcludeFromText="0" ExcludeCaption="0" Visibility="1" CarryForward="0" Optional="1">
          <Answer AnswerId="20962" OrderNumber="1" OptionText="Overfladisk sår."/>
          <Answer AnswerId="20963" OrderNumber="2" OptionText="Dypt sår."/>
          <Answer AnswerId="20964" OrderNumber="3" OptionText="Dypt sår med synlig sene/benvev."/>
        </FormItem>
      </Item>
      <Item ItemId="4622" ItemType="1" VarName="ULCER1_LENGTH_MM" LoincScale="QN" UnitStr="mm" DisplayFormat="">
        <FormItem ItemHeader="Lengde" ItemText="Sårets lengde (mm)" ItemHelp="Største diameter" MinExpression="0" MaxExpression="200" ExcludeFromText="0" ExcludeCaption="0" Visibility="1" CarryForward="0" Optional="1">
          <Answer/>
        </FormItem>
      </Item>
      <Item ItemId="4623" ItemType="1" VarName="ULCER1_WIDTH_MM" LoincScale="QN" UnitStr="mm" DisplayFormat="">
        <FormItem ItemHeader="Bredde" ItemText="Sårets bredde (mm)" ItemHelp="På tvers av største diameter" MinExpression="0" MaxExpression="200" ExcludeFromText="0" ExcludeCaption="0" Visibility="1" CarryForward="0" Optional="1">
          <Answer/>
        </FormItem>
      </Item>
      <Item ItemId="4026" ItemType="2" VarName="ULCER1_SECRETION" LoincScale="ORD" DisplayFormat="Vertical">
        <FormItem ItemText="Sekresjon" ItemHelp="" MinExpression="" MaxExpression="" ExcludeFromText="0" ExcludeCaption="0" Visibility="1" CarryForward="0" Optional="1">
          <Answer AnswerId="21004" OrderNumber="1" OptionText="Tørt sår."/>
          <Answer AnswerId="21005" OrderNumber="2" OptionText="Rent granulerende sår."/>
          <Answer AnswerId="21006" OrderNumber="3" OptionText="Væskende sår."/>
          <Answer AnswerId="21007" OrderNumber="4" OptionText="Pussbelagt sår."/>
        </FormItem>
      </Item>
      <Item ItemId="4030" ItemType="2" VarName="ULCER1_RUBOR" LoincScale="ORD" DisplayFormat="Vertical">
        <FormItem ItemHeader="Infeksjonstegn" ItemText="Rubor" ItemHelp="" MinExpression="" MaxExpression="" ExcludeFromText="0" ExcludeCaption="0" Visibility="1" CarryForward="0" Optional="1">
          <Answer AnswerId="21030" OrderNumber="1" OptionText="ikke tilstede."/>
          <Answer AnswerId="21031" OrderNumber="2" OptionText="inntil 2 cm rundt såret."/>
          <Answer AnswerId="21032" OrderNumber="3" OptionText="over 2 cm rundt såret."/>
        </FormItem>
      </Item>
      <Item ItemId="4034" ItemType="2" VarName="ULCER1_NECROSIS" LoincScale="ORD" DisplayFormat="Vertical">
        <FormItem ItemText="Sårnekrose" ItemHelp="" MinExpression="" MaxExpression="" ExcludeFromText="0" ExcludeCaption="0" Visibility="1" CarryForward="0" Optional="1">
          <Answer AnswerId="21051" OrderNumber="1" OptionText="Ingen nekrose."/>
          <Answer AnswerId="21052" OrderNumber="2" OptionText="Gul nekrose."/>
          <Answer AnswerId="21053" OrderNumber="3" OptionText="Tørr svart nekrose."/>
          <Answer AnswerId="22875" OrderNumber="4" OptionText="Fuktig svart nekrose."/>
          <Answer AnswerId="25106" OrderNumber="5" OptionText="Gul og svart nekrose."/>
        </FormItem>
      </Item>
      <Item ItemId="4038" ItemType="2" VarName="ULCER1_SUSPM86" LoincScale="ORD" DisplayFormat="Vertical">
        <FormItem ItemText="Osteomyelitt" ItemHelp="" MinExpression="" MaxExpression="" ExcludeFromText="0" ExcludeCaption="0" Visibility="1" CarryForward="0" Optional="1">
          <Answer AnswerId="21072" OrderNumber="1" OptionText="Ja" VerboseText="Mistenker osteomyelitt." ShortCode="J"/>
          <Answer AnswerId="21073" OrderNumber="2" OptionText="Nei*" ShortCode="N"/>
          <Answer AnswerId="21074" OrderNumber="3" OptionText="Usikker" VerboseText="Mulig osteomyelitt?"/>
        </FormItem>
      </Item>
      <Item ItemId="4381" ItemType="4" VarName="ULCER1_LOC_TEXT" LoincScale="NAR" DisplayFormat="" Multiline="0">
        <FormItem ItemText="Kommentar" ItemHelp="" MinExpression="" MaxExpression="" ExcludeFromText="0" ExcludeCaption="0" Visibility="1" CarryForward="1" Optional="1">
          <Answer/>
        </FormItem>
      </Item>
      <Item ItemId="4042" ItemType="5" VarName="ULCER1_BACTUS" LoincScale="DATE" DisplayFormat="">
        <FormItem ItemText="Dato siste bactus fra dette såret" ItemHelp="" MinExpression="" MaxExpression="NOW" ExcludeFromText="0" ExcludeCaption="0" Visibility="1" CarryForward="0" Optional="0">
          <Answer/>
        </FormItem>
      </Item>
      <Item ItemId="4281" ItemType="2" VarName="ULCER1_DETAIL" LoincScale="ORD" DisplayFormat="Vertical">
        <FormItem ItemText="Registrere lokalbehandling?" ItemHelp="" MinExpression="" MaxExpression="" ExcludeFromText="1" ExcludeCaption="0" Visibility="1" CarryForward="0" Optional="1">
          <Answer AnswerId="22954" OrderNumber="1" OptionText="Ja"/>
          <Answer AnswerId="22955" OrderNumber="2" OptionText="Nei" ShortCode="N"/>
        </FormItem>
      </Item>
    </Page>
    <Page PageTitle="Lokalbehandling">
      <Item ItemId="4268" ItemType="2" VarName="ULCER1_NACL" LoincScale="ORD" DisplayFormat="Vertical">
        <FormItem ItemText="Skylling med NaCl 0,9% kroppstemperert." ItemHelp="" MinExpression="" MaxExpression="" ExcludeFromText="0" ExcludeCaption="0" Visibility="1" CarryForward="1" Optional="1">
          <Answer AnswerId="22900" OrderNumber="1" OptionText="Ja" VerboseText="Skylling med NaCl 0,9% kroppstemperert." ShortCode="J"/>
          <Answer AnswerId="22901" OrderNumber="2" OptionText="Nei*" ShortCode="N"/>
        </FormItem>
      </Item>
      <Item ItemId="6396" ItemType="2" VarName="VAR6396" LoincScale="ORD" DisplayFormat="">
        <FormItem ItemText="Prontosan" ItemHelp="" MinExpression="" MaxExpression="" ExcludeFromText="0" ExcludeCaption="0" Visibility="1" CarryForward="0" Optional="1">
          <Answer AnswerId="33828" OrderNumber="1" OptionText="Ja" VerboseText="Prontosan sårskyllevæske i 10 min." ShortCode="J"/>
          <Answer AnswerId="33829" OrderNumber="2" OptionText="Nei*" ShortCode="N"/>
        </FormItem>
      </Item>
      <Item ItemId="4290" ItemType="2" VarName="ULCER1_DRESSING" LoincScale="ORD" DisplayFormat="Vertical">
        <FormItem ItemText="Bandasje" ItemHelp="" MinExpression="" MaxExpression="" ExcludeFromText="0" ExcludeCaption="0" Visibility="1" CarryForward="1" Optional="1">
          <Answer AnswerId="23007" OrderNumber="1" OptionText="Ingen" VerboseText="Ingen bandasje."/>
          <Answer AnswerId="23008" OrderNumber="2" OptionText="Tørrbandasje."/>
          <Answer AnswerId="23009" OrderNumber="3" OptionText="med aktiv behandling*"/>
        </FormItem>
      </Item>
    </Page>
    <Page PageTitle="Aktiv bandasje*">
      <Item ItemId="4269" ItemType="2" VarName="ULCER1_EDGE" LoincScale="ORD" DisplayFormat="Vertical">
        <FormItem ItemText="Sårkant behandling" ItemHelp="" MinExpression="" MaxExpression="" ExcludeFromText="0" ExcludeCaption="0" Visibility="1" CarryForward="1" Optional="1">
          <Answer AnswerId="22902" OrderNumber="1" OptionText="Nei*" ShortCode="N"/>
          <Answer AnswerId="22903" OrderNumber="2" OptionText="Sink" VerboseText="Sink i sårkantene,"/>
          <Answer AnswerId="23006" OrderNumber="3" OptionText="Cavilon" VerboseText="Cavilon i sårkantene,"/>
        </FormItem>
      </Item>
      <Item ItemId="4272" ItemType="2" VarName="ULCER1_INTRASITE" LoincScale="ORD" DisplayFormat="Vertical">
        <FormItem ItemText="IntraSite gel." ItemHelp="" MinExpression="" MaxExpression="" ExcludeFromText="0" ExcludeCaption="0" Visibility="1" CarryForward="1" Optional="1">
          <Answer AnswerId="22914" OrderNumber="1" OptionText="Ja" VerboseText="IntraSite gel," ShortCode="J"/>
          <Answer AnswerId="22915" OrderNumber="2" OptionText="Nei*" ShortCode="N"/>
        </FormItem>
      </Item>
      <Item ItemId="6397" ItemType="2" VarName="VAR6397" LoincScale="ORD" DisplayFormat="">
        <FormItem ItemText="Prontosan gel" ItemHelp="" MinExpression="" MaxExpression="" ExcludeFromText="0" ExcludeCaption="0" Visibility="1" CarryForward="0" Optional="1">
          <Answer AnswerId="33838" OrderNumber="1" OptionText="Ja" VerboseText="Prontosan gel." ShortCode="J"/>
          <Answer AnswerId="33839" OrderNumber="2" OptionText="Nei*" ShortCode="N"/>
        </FormItem>
      </Item>
      <Item ItemId="4271" ItemType="2" VarName="ULCER1_SILVER" LoincScale="ORD" DisplayFormat="">
        <FormItem ItemText="Sølvbandasje" ItemHelp="" MinExpression="" MaxExpression="" ExcludeFromText="0" ExcludeCaption="0" Visibility="1" CarryForward="0" Optional="1">
          <Answer AnswerId="22910" OrderNumber="1" OptionText="Nei*" ShortCode="N"/>
          <Answer AnswerId="22911" OrderNumber="2" OptionText="Flamazine."/>
          <Answer AnswerId="23002" OrderNumber="3" OptionText="Acticoat."/>
          <Answer AnswerId="23003" OrderNumber="4" OptionText="Aquacel Ag."/>
          <Answer AnswerId="25083" OrderNumber="5" OptionText="Acticoat absorbent."/>
          <Answer AnswerId="33827" OrderNumber="6" OptionText="Mepilex Ag."/>
        </FormItem>
      </Item>
      <Item ItemId="4276" ItemType="2" VarName="ULCER1_SORBACT" LoincScale="ORD" DisplayFormat="Vertical">
        <FormItem ItemText="Sorbact" ItemHelp="" MinExpression="" MaxExpression="" ExcludeFromText="0" ExcludeCaption="0" Visibility="1" CarryForward="1" Optional="1">
          <Answer AnswerId="22934" OrderNumber="1" OptionText="Ja" VerboseText="Sorbact." ShortCode="J"/>
          <Answer AnswerId="22935" OrderNumber="2" OptionText="Nei*" ShortCode="N"/>
        </FormItem>
      </Item>
      <Item ItemId="4277" ItemType="2" VarName="ULCER1_PU" LoincScale="ORD" DisplayFormat="Vertical">
        <FormItem ItemText="Polyuretanbandasje" ItemHelp="" MinExpression="" MaxExpression="" ExcludeFromText="0" ExcludeCaption="0" Visibility="1" CarryForward="1" Optional="1">
          <Answer AnswerId="22938" OrderNumber="1" OptionText="Ja" VerboseText="Polyuretanbandasje," ShortCode="J"/>
          <Answer AnswerId="22939" OrderNumber="2" OptionText="Nei*" ShortCode="N"/>
        </FormItem>
      </Item>
      <Item ItemId="4278" ItemType="2" VarName="ULCER1_HYPAFIX" LoincScale="ORD" DisplayFormat="Vertical">
        <FormItem ItemText="Hypafix" ItemHelp="" MinExpression="" MaxExpression="" ExcludeFromText="0" ExcludeCaption="0" Visibility="1" CarryForward="1" Optional="1">
          <Answer AnswerId="22942" OrderNumber="1" OptionText="Ja" VerboseText="Hypafix." ShortCode="J"/>
          <Answer AnswerId="22943" OrderNumber="2" OptionText="Nei*" ShortCode="N"/>
        </FormItem>
      </Item>
      <Item ItemId="4279" ItemType="2" VarName="ULCER1_TUBEGAS" LoincScale="ORD" DisplayFormat="Vertical">
        <FormItem ItemText="Tubegas" ItemHelp="" MinExpression="" MaxExpression="" ExcludeFromText="0" ExcludeCaption="0" Visibility="1" CarryForward="1" Optional="1">
          <Answer AnswerId="22946" OrderNumber="1" OptionText="Ja" VerboseText="Tubegas." ShortCode="J"/>
          <Answer AnswerId="22947" OrderNumber="2" OptionText="Nei*" ShortCode="N"/>
        </FormItem>
      </Item>
      <Item ItemId="4280" ItemType="2" VarName="ULCER1_TUBIFAST" LoincScale="ORD" DisplayFormat="Vertical">
        <FormItem ItemText="Tubifast" ItemHelp="" MinExpression="" MaxExpression="" ExcludeFromText="0" ExcludeCaption="0" Visibility="1" CarryForward="1" Optional="1">
          <Answer AnswerId="22950" OrderNumber="1" OptionText="Ja" VerboseText="Tubifast." ShortCode="J"/>
          <Answer AnswerId="22951" OrderNumber="2" OptionText="Nei*" ShortCode="N"/>
        </FormItem>
      </Item>
    </Page>
    <Page PageTitle="Kommentar første fotsår*">
      <Item ItemId="3254" ItemType="4" VarName="ULCER1_COMMENT" LoincScale="NAR" DisplayFormat="" Multiline="1">
        <FormItem ItemText="Kommentar" ItemHelp="" MinExpression="" MaxExpression="" ExcludeFromText="0" ExcludeCaption="0" Visibility="1" CarryForward="0" Optional="0">
          <Answer/>
        </FormItem>
      </Item>
    </Page>
    <Page PageTitle="Sår 2">
      <Item ItemId="3255" ItemType="2" VarName="ULCER2_LATERALITY" LoincScale="ORD" DisplayFormat="Vertical">
        <FormItem ItemText="Side" ItemHelp="" MinExpression="" MaxExpression="" ExcludeFromText="0" ExcludeCaption="0" Visibility="1" CarryForward="1" Optional="0">
          <Answer AnswerId="16245" OrderNumber="1" OptionText="Venstre side."/>
          <Answer AnswerId="16246" OrderNumber="2" OptionText="Høyre side."/>
        </FormItem>
      </Item>
      <Item ItemId="4012" ItemType="2" VarName="ULCER2_LOCATION" LoincScale="ORD" DisplayFormat="Vertical">
        <FormItem ItemText="Lokalisasjon" ItemHelp="" MinExpression="" MaxExpression="" ExcludeFromText="0" ExcludeCaption="0" Visibility="1" CarryForward="1" Optional="0">
          <Answer AnswerId="20919" OrderNumber="1" OptionText="Stortå"/>
          <Answer AnswerId="20920" OrderNumber="2" OptionText="Andre tær*"/>
          <Answer AnswerId="20921" OrderNumber="3" OptionText="Metatars"/>
          <Answer AnswerId="20922" OrderNumber="4" OptionText="Hæl"/>
          <Answer AnswerId="20923" OrderNumber="5" OptionText="Annen*"/>
        </FormItem>
      </Item>
      <Item ItemId="3270" ItemType="5" VarName="ULCER2_SINCE" LoincScale="DATE" DisplayFormat="">
        <FormItem ItemText="Hatt siden" ItemHelp="" MinExpression="" MaxExpression="" ExcludeFromText="0" ExcludeCaption="0" Visibility="1" CarryForward="1" Optional="0">
          <Answer/>
        </FormItem>
      </Item>
      <Item ItemId="4015" ItemType="2" VarName="ULCER2_DEPTH" LoincScale="ORD" DisplayFormat="Vertical">
        <FormItem ItemText="Sårets dybde" ItemHelp="" MinExpression="" MaxExpression="" ExcludeFromText="0" ExcludeCaption="0" Visibility="1" CarryForward="0" Optional="1">
          <Answer AnswerId="20959" OrderNumber="1" OptionText="Overfladisk sår."/>
          <Answer AnswerId="20960" OrderNumber="2" OptionText="Dypt sår."/>
          <Answer AnswerId="20961" OrderNumber="3" OptionText="Dypt sår med synlig sene/benvev."/>
        </FormItem>
      </Item>
      <Item ItemId="4624" ItemType="1" VarName="ULCER2_LENGTH_MM" LoincScale="QN" UnitStr="mm" DisplayFormat="">
        <FormItem ItemText="Sårets lengde (mm)" ItemHelp="Største diameter" MinExpression="0" MaxExpression="200" ExcludeFromText="0" ExcludeCaption="0" Visibility="1" CarryForward="0" Optional="1">
          <Answer/>
        </FormItem>
      </Item>
      <Item ItemId="4625" ItemType="1" VarName="ULCER2_WIDTH_MM" LoincScale="QN" UnitStr="mm" DisplayFormat="">
        <FormItem ItemText="Sårets bredde (mm)" ItemHelp="På tvers av største diameter" MinExpression="0" MaxExpression="200" ExcludeFromText="0" ExcludeCaption="0" Visibility="1" CarryForward="0" Optional="1">
          <Answer/>
        </FormItem>
      </Item>
      <Item ItemId="4025" ItemType="2" VarName="ULCER2_SECRETION" LoincScale="ORD" DisplayFormat="Vertical">
        <FormItem ItemText="Sekresjon" ItemHelp="" MinExpression="" MaxExpression="" ExcludeFromText="0" ExcludeCaption="0" Visibility="1" CarryForward="0" Optional="1">
          <Answer AnswerId="20996" OrderNumber="1" OptionText="Tørt sår."/>
          <Answer AnswerId="20997" OrderNumber="2" OptionText="Rent granulerende sår."/>
          <Answer AnswerId="20998" OrderNumber="3" OptionText="Væskende sår."/>
          <Answer AnswerId="20999" OrderNumber="4" OptionText="Pussbelagt sår."/>
        </FormItem>
      </Item>
      <Item ItemId="4029" ItemType="2" VarName="ULCER2_RUBOR" LoincScale="ORD" DisplayFormat="Vertical">
        <FormItem ItemHeader="Infeksjonstegn" ItemText="Rubor" ItemHelp="" MinExpression="" MaxExpression="" ExcludeFromText="0" ExcludeCaption="0" Visibility="1" CarryForward="0" Optional="1">
          <Answer AnswerId="21024" OrderNumber="1" OptionText="ikke tilstede."/>
          <Answer AnswerId="21025" OrderNumber="2" OptionText="inntil 2 cm rundt såret."/>
          <Answer AnswerId="21026" OrderNumber="3" OptionText="over 2 cm rundt såret."/>
        </FormItem>
      </Item>
      <Item ItemId="4033" ItemType="2" VarName="ULCER2_NECROSIS" LoincScale="ORD" DisplayFormat="Vertical">
        <FormItem ItemText="Sårnekrose" ItemHelp="" MinExpression="" MaxExpression="" ExcludeFromText="0" ExcludeCaption="0" Visibility="1" CarryForward="0" Optional="1">
          <Answer AnswerId="21045" OrderNumber="1" OptionText="Ingen nekrose."/>
          <Answer AnswerId="21046" OrderNumber="2" OptionText="Gul nekrose."/>
          <Answer AnswerId="21047" OrderNumber="3" OptionText="Tørr svart nekrose."/>
          <Answer AnswerId="22879" OrderNumber="4" OptionText="Fuktig svart nekrose."/>
          <Answer AnswerId="25116" OrderNumber="5" OptionText="Gul og svart nekrose."/>
        </FormItem>
      </Item>
      <Item ItemId="4037" ItemType="2" VarName="ULCER2_SUSPM86" LoincScale="ORD" DisplayFormat="Vertical">
        <FormItem ItemText="Osteomyelitt" ItemHelp="" MinExpression="" MaxExpression="" ExcludeFromText="0" ExcludeCaption="0" Visibility="1" CarryForward="0" Optional="1">
          <Answer AnswerId="21066" OrderNumber="1" OptionText="Ja" VerboseText="Mistenker osteomyelitt." ShortCode="J"/>
          <Answer AnswerId="21067" OrderNumber="2" OptionText="Nei*" ShortCode="N"/>
          <Answer AnswerId="21068" OrderNumber="3" OptionText="Usikker" VerboseText="Mulig osteomyelitt?"/>
        </FormItem>
      </Item>
      <Item ItemId="4383" ItemType="4" VarName="ULCER2_LOC_TEXT" LoincScale="NAR" DisplayFormat="" Multiline="0">
        <FormItem ItemText="Kommentar" ItemHelp="" MinExpression="" MaxExpression="" ExcludeFromText="0" ExcludeCaption="0" Visibility="1" CarryForward="1" Optional="1">
          <Answer/>
        </FormItem>
      </Item>
      <Item ItemId="4041" ItemType="5" VarName="ULCER2_BACTUS" LoincScale="DATE" DisplayFormat="">
        <FormItem ItemText="Dato siste bactus fra dette såret" ItemHelp="" MinExpression="" MaxExpression="NOW" ExcludeFromText="0" ExcludeCaption="0" Visibility="1" CarryForward="1" Optional="1">
          <Answer/>
        </FormItem>
      </Item>
      <Item ItemId="3256" ItemType="4" VarName="ULCER2_COMMENT" LoincScale="NAR" DisplayFormat="" Multiline="1">
        <FormItem ItemText="Kommentar" ItemHelp="" MinExpression="" MaxExpression="" ExcludeFromText="0" ExcludeCaption="0" Visibility="1" CarryForward="0" Optional="0">
          <Answer/>
        </FormItem>
      </Item>
    </Page>
    <Page PageTitle="Sår 3">
      <Item ItemId="3257" ItemType="2" VarName="ULCER3_LATERALITY" LoincScale="ORD" DisplayFormat="Vertical">
        <FormItem ItemText="Side" ItemHelp="" MinExpression="" MaxExpression="" ExcludeFromText="0" ExcludeCaption="0" Visibility="1" CarryForward="1" Optional="0">
          <Answer AnswerId="16247" OrderNumber="1" OptionText="Venstre side."/>
          <Answer AnswerId="16248" OrderNumber="2" OptionText="Høyre side."/>
        </FormItem>
      </Item>
      <Item ItemId="4013" ItemType="2" VarName="ULCER3_LOCATION" LoincScale="ORD" DisplayFormat="Vertical">
        <FormItem ItemText="Lokalisasjon" ItemHelp="" MinExpression="" MaxExpression="" ExcludeFromText="0" ExcludeCaption="0" Visibility="1" CarryForward="1" Optional="0">
          <Answer AnswerId="20939" OrderNumber="1" OptionText="Stortå"/>
          <Answer AnswerId="20940" OrderNumber="2" OptionText="Andre tær*"/>
          <Answer AnswerId="20941" OrderNumber="3" OptionText="Metatars"/>
          <Answer AnswerId="20942" OrderNumber="4" OptionText="Hæl"/>
          <Answer AnswerId="20943" OrderNumber="5" OptionText="Annen*"/>
        </FormItem>
      </Item>
      <Item ItemId="3271" ItemType="5" VarName="ULCER3_SINCE" LoincScale="DATE" DisplayFormat="">
        <FormItem ItemText="Hatt siden" ItemHelp="" MinExpression="" MaxExpression="" ExcludeFromText="0" ExcludeCaption="0" Visibility="1" CarryForward="1" Optional="0">
          <Answer/>
        </FormItem>
      </Item>
      <Item ItemId="4017" ItemType="2" VarName="ULCER3_DEPTH" LoincScale="ORD" DisplayFormat="Vertical">
        <FormItem ItemText="Sårets dybde" ItemHelp="" MinExpression="" MaxExpression="" ExcludeFromText="0" ExcludeCaption="0" Visibility="1" CarryForward="0" Optional="1">
          <Answer AnswerId="20971" OrderNumber="1" OptionText="Overfladisk sår."/>
          <Answer AnswerId="20972" OrderNumber="2" OptionText="Dypt sår."/>
          <Answer AnswerId="20973" OrderNumber="3" OptionText="Dypt sår med synlig sene/benvev."/>
        </FormItem>
      </Item>
      <Item ItemId="4626" ItemType="1" VarName="ULCER3_LENGTH_MM" LoincScale="QN" UnitStr="mm" DisplayFormat="">
        <FormItem ItemText="Sårets lengde (mm)" ItemHelp="Største diameter" MinExpression="0" MaxExpression="200" ExcludeFromText="0" ExcludeCaption="0" Visibility="1" CarryForward="0" Optional="1">
          <Answer/>
        </FormItem>
      </Item>
      <Item ItemId="4627" ItemType="1" VarName="ULCER3_WIDTH_MM" LoincScale="QN" UnitStr="mm" DisplayFormat="">
        <FormItem ItemText="Sårets bredde (mm)" ItemHelp="På tvers av største diameter" MinExpression="0" MaxExpression="200" ExcludeFromText="0" ExcludeCaption="0" Visibility="1" CarryForward="0" Optional="1">
          <Answer/>
        </FormItem>
      </Item>
      <Item ItemId="4024" ItemType="2" VarName="ULCER3_SECRETION" LoincScale="ORD" DisplayFormat="Vertical">
        <FormItem ItemText="Sekresjon" ItemHelp="" MinExpression="" MaxExpression="" ExcludeFromText="0" ExcludeCaption="0" Visibility="1" CarryForward="0" Optional="1">
          <Answer AnswerId="20988" OrderNumber="1" OptionText="Tørt sår."/>
          <Answer AnswerId="20989" OrderNumber="2" OptionText="Rent granulerende sår."/>
          <Answer AnswerId="20990" OrderNumber="3" OptionText="Væskende sår."/>
          <Answer AnswerId="20991" OrderNumber="4" OptionText="Pussbelagt sår."/>
        </FormItem>
      </Item>
      <Item ItemId="4028" ItemType="2" VarName="ULCER3_RUBOR" LoincScale="ORD" DisplayFormat="Vertical">
        <FormItem ItemHeader="Infeksjonstegn" ItemText="Rubor" ItemHelp="" MinExpression="" MaxExpression="" ExcludeFromText="0" ExcludeCaption="0" Visibility="1" CarryForward="0" Optional="1">
          <Answer AnswerId="21018" OrderNumber="1" OptionText="ikke tilstede."/>
          <Answer AnswerId="21019" OrderNumber="2" OptionText="inntil 2 cm rundt såret."/>
          <Answer AnswerId="21020" OrderNumber="3" OptionText="over 2 cm rundt såret."/>
        </FormItem>
      </Item>
      <Item ItemId="4032" ItemType="2" VarName="ULCER3_NECROSIS" LoincScale="ORD" DisplayFormat="Vertical">
        <FormItem ItemText="Sårnekrose" ItemHelp="" MinExpression="" MaxExpression="" ExcludeFromText="0" ExcludeCaption="0" Visibility="1" CarryForward="0" Optional="1">
          <Answer AnswerId="21039" OrderNumber="1" OptionText="Ingen nekrose."/>
          <Answer AnswerId="21040" OrderNumber="2" OptionText="Gul nekrose."/>
          <Answer AnswerId="21041" OrderNumber="3" OptionText="Tørr svart nekrose."/>
          <Answer AnswerId="22883" OrderNumber="4" OptionText="Fuktig svart nekrose."/>
          <Answer AnswerId="25111" OrderNumber="5" OptionText="Gul og svart nekrose."/>
        </FormItem>
      </Item>
      <Item ItemId="4036" ItemType="2" VarName="ULCER3_SUSPM86" LoincScale="ORD" DisplayFormat="Vertical">
        <FormItem ItemText="Osteomyelitt" ItemHelp="" MinExpression="" MaxExpression="" ExcludeFromText="0" ExcludeCaption="0" Visibility="1" CarryForward="0" Optional="1">
          <Answer AnswerId="21060" OrderNumber="1" OptionText="Ja" VerboseText="Mistanker osteomyelitt." ShortCode="J"/>
          <Answer AnswerId="21061" OrderNumber="2" OptionText="Nei*" ShortCode="N"/>
          <Answer AnswerId="21062" OrderNumber="3" OptionText="Usikker" VerboseText="Mulig osteomyelitt?"/>
        </FormItem>
      </Item>
      <Item ItemId="4384" ItemType="4" VarName="ULCER3_LOC_TEXT" LoincScale="NAR" DisplayFormat="" Multiline="0">
        <FormItem ItemText="Kommentar" ItemHelp="" MinExpression="" MaxExpression="" ExcludeFromText="0" ExcludeCaption="0" Visibility="1" CarryForward="1" Optional="1">
          <Answer/>
        </FormItem>
      </Item>
      <Item ItemId="4040" ItemType="5" VarName="ULCER3_BACTUS" LoincScale="DATE" DisplayFormat="">
        <FormItem ItemText="Dato siste bactus fra dette såret" ItemHelp="" MinExpression="" MaxExpression="NOW" ExcludeFromText="0" ExcludeCaption="0" Visibility="1" CarryForward="1" Optional="1">
          <Answer/>
        </FormItem>
      </Item>
      <Item ItemId="3258" ItemType="4" VarName="ULCER3_COMMENT" LoincScale="NAR" DisplayFormat="" Multiline="1">
        <FormItem ItemText="Kommentar" ItemHelp="" MinExpression="" MaxExpression="" ExcludeFromText="0" ExcludeCaption="0" Visibility="1" CarryForward="0" Optional="0">
          <Answer/>
        </FormItem>
      </Item>
    </Page>
    <Page PageTitle="Avlastningstiltak">
      <Item ItemId="4629" ItemType="2" VarName="FOOT_ORTHO_ENG" LoincScale="ORD" DisplayFormat="Vertical">
        <FormItem ItemText="Tilsyn av ortopediingeniør" ItemHelp="" MinExpression="" MaxExpression="" ExcludeFromText="0" ExcludeCaption="0" Visibility="1" CarryForward="1" Optional="1">
          <Answer AnswerId="25084" OrderNumber="1" OptionText="Ja" VerboseText="Tilsett av ortopediingeniør." ShortCode="J"/>
          <Answer AnswerId="25085" OrderNumber="2" OptionText="Nei*" ShortCode="N"/>
        </FormItem>
      </Item>
    </Page>
    <Page PageTitle="Ortopedisk behandling*">
      <Item ItemId="4631" ItemType="5" VarName="FOOT_ORTHO_DATE" LoincScale="DATE" DisplayFormat="">
        <FormItem ItemText="Dato" ItemHelp="" MinExpression="" MaxExpression="" ExcludeFromText="0" ExcludeCaption="0" Visibility="1" CarryForward="1" Optional="1">
          <Answer/>
        </FormItem>
      </Item>
      <Item ItemId="6395" ItemType="4" VarName="VAR6395" LoincScale="NAR" DisplayFormat="" Multiline="1">
        <FormItem ItemText="Kommentar" ItemHelp="" MinExpression="" MaxExpression="" ExcludeFromText="0" ExcludeCaption="0" Visibility="1" CarryForward="0" Optional="1">
          <Answer/>
        </FormItem>
      </Item>
      <Item ItemId="4283" ItemType="2" VarName="FOOT_RELIEF_BEDS" LoincScale="ORD" DisplayFormat="Vertical">
        <FormItem ItemText="Fotsenger" ItemHelp="" MinExpression="" MaxExpression="" ExcludeFromText="0" ExcludeCaption="0" Visibility="1" CarryForward="1" Optional="1">
          <Answer AnswerId="22960" OrderNumber="1" OptionText="Ja" VerboseText="Fotsenger." ShortCode="J"/>
          <Answer AnswerId="22961" OrderNumber="2" OptionText="Nei*" ShortCode="N"/>
        </FormItem>
      </Item>
      <Item ItemId="4284" ItemType="2" VarName="FOOT_RELIEF_SHOES" LoincScale="ORD" DisplayFormat="Vertical">
        <FormItem ItemText="Spesialsko" ItemHelp="" MinExpression="" MaxExpression="" ExcludeFromText="0" ExcludeCaption="0" Visibility="1" CarryForward="1" Optional="1">
          <Answer AnswerId="22964" OrderNumber="1" OptionText="Ja" VerboseText="Spesialsko." ShortCode="J"/>
          <Answer AnswerId="22965" OrderNumber="2" OptionText="Nei*" ShortCode="N"/>
        </FormItem>
      </Item>
      <Item ItemId="4289" ItemType="2" VarName="FOOT_ORTHOSIS_LEFT" LoincScale="ORD" DisplayFormat="Vertical">
        <FormItem ItemText="Ortose venstre fot" ItemHelp="" MinExpression="" MaxExpression="" ExcludeFromText="0" ExcludeCaption="0" Visibility="1" CarryForward="1" Optional="1">
          <Answer AnswerId="22984" OrderNumber="1" OptionText="Nei*"/>
          <Answer AnswerId="22985" OrderNumber="2" OptionText="Silikon" VerboseText="Silikonortose V."/>
          <Answer AnswerId="22990" OrderNumber="3" OptionText="Total Cast" VerboseText="Total cast ortose V."/>
          <Answer AnswerId="23518" OrderNumber="4" OptionText="Total Charcot" VerboseText="Total Charcot ortose V."/>
        </FormItem>
      </Item>
      <Item ItemId="4291" ItemType="2" VarName="FOOT_ORTHOSIS_RIGHT" LoincScale="ORD" DisplayFormat="Vertical">
        <FormItem ItemText="Ortose høyre fot" ItemHelp="" MinExpression="" MaxExpression="" ExcludeFromText="0" ExcludeCaption="0" Visibility="1" CarryForward="1" Optional="1">
          <Answer AnswerId="23059" OrderNumber="1" OptionText="Nei*"/>
          <Answer AnswerId="23060" OrderNumber="2" OptionText="Silikon" VerboseText="Silikonortose H."/>
          <Answer AnswerId="23061" OrderNumber="3" OptionText="Total Cast" VerboseText="Total cast ortose H."/>
          <Answer AnswerId="23514" OrderNumber="4" OptionText="Total Charcot" VerboseText="Total Charcot ortose H."/>
        </FormItem>
      </Item>
      <Item ItemId="4630" ItemType="4" VarName="FOOT_ORTHO_COMMENT" LoincScale="NAR" DisplayFormat="" Multiline="1">
        <FormItem ItemText="Kommentar" ItemHelp="" MinExpression="" MaxExpression="" ExcludeFromText="0" ExcludeCaption="0" Visibility="1" CarryForward="1" Optional="1">
          <Answer/>
        </FormItem>
      </Item>
    </Page>
    <Page PageTitle="Annen avlastning*">
      <Item ItemId="4285" ItemType="2" VarName="FOOT_RELIEF_FILT" LoincScale="ORD" DisplayFormat="Vertical">
        <FormItem ItemText="Filtavlastning" ItemHelp="" MinExpression="" MaxExpression="" ExcludeFromText="0" ExcludeCaption="0" Visibility="1" CarryForward="0" Optional="1">
          <Answer AnswerId="22968" OrderNumber="1" OptionText="Ja" VerboseText="Filtavlastning." ShortCode="J"/>
          <Answer AnswerId="22969" OrderNumber="2" OptionText="Nei*" ShortCode="N"/>
        </FormItem>
      </Item>
      <Item ItemId="4286" ItemType="2" VarName="FOOT_RELIEF_PAD" LoincScale="ORD" DisplayFormat="Vertical">
        <FormItem ItemText="Pølseavlastning." ItemHelp="" MinExpression="" MaxExpression="" ExcludeFromText="0" ExcludeCaption="0" Visibility="1" CarryForward="0" Optional="1">
          <Answer AnswerId="22972" OrderNumber="1" OptionText="Ja" VerboseText="Pølseavlastning" ShortCode="J"/>
          <Answer AnswerId="22973" OrderNumber="2" OptionText="Nei*" ShortCode="N"/>
        </FormItem>
      </Item>
      <Item ItemId="4287" ItemType="2" VarName="FOOT_RELIEF_TUBEFOAM" LoincScale="ORD" DisplayFormat="Vertical">
        <FormItem ItemText="Tubefoam" ItemHelp="" MinExpression="" MaxExpression="" ExcludeFromText="0" ExcludeCaption="0" Visibility="1" CarryForward="0" Optional="1">
          <Answer AnswerId="22976" OrderNumber="1" OptionText="Ja" VerboseText="Tubefoam." ShortCode="J"/>
          <Answer AnswerId="22977" OrderNumber="2" OptionText="Nei*" ShortCode="N"/>
        </FormItem>
      </Item>
      <Item ItemId="6393" ItemType="2" VarName="VAR6393" LoincScale="ORD" DisplayFormat="">
        <FormItem ItemText="Silikonortose" ItemHelp="" MinExpression="" MaxExpression="" ExcludeFromText="0" ExcludeCaption="0" Visibility="1" CarryForward="0" Optional="1">
          <Answer AnswerId="33812" OrderNumber="1" OptionText="Ja" VerboseText="Silikonortose." ShortCode="J"/>
          <Answer AnswerId="33813" OrderNumber="2" OptionText="Nei*" ShortCode="N"/>
        </FormItem>
      </Item>
      <Item ItemId="6394" ItemType="2" VarName="VAR6394" LoincScale="ORD" DisplayFormat="">
        <FormItem ItemText="Plastazote" ItemHelp="" MinExpression="" MaxExpression="" ExcludeFromText="0" ExcludeCaption="0" Visibility="1" CarryForward="0" Optional="1">
          <Answer AnswerId="33818" OrderNumber="1" OptionText="Ja" VerboseText="Plastazote." ShortCode="J"/>
          <Answer AnswerId="33819" OrderNumber="2" OptionText="Nei*" ShortCode="N"/>
        </FormItem>
      </Item>
    </Page>
    <Page PageTitle="Vurdering og avtaler">
      <Item ItemId="4265" ItemType="4" VarName="DIAPOL_FOOT_EVAL" LoincScale="NAR" DisplayFormat="" Multiline="1">
        <FormItem ItemText="Vurdering og avtaler" ItemHelp="" MinExpression="" MaxExpression="" ExcludeFromText="0" ExcludeCaption="0" Visibility="1" CarryForward="0" Optional="1">
          <Answer/>
        </FormItem>
      </Item>
      <Item ItemId="4266" ItemType="4" VarName="DIAPOL_FOOT_NEXT" LoincScale="NAR" DisplayFormat="" Multiline="0">
        <FormItem ItemText="Neste kontroll:" ItemHelp="" MinExpression="" MaxExpression="" ExcludeFromText="0" ExcludeCaption="0" Visibility="1" CarryForward="0" Optional="1">
          <Answer/>
        </FormItem>
      </Item>
      <Item ItemId="4267" ItemType="2" VarName="DIAPOL_FOOT_HOMECARE" LoincScale="ORD" DisplayFormat="">
        <FormItem ItemText="Følges opp av hjemmesykepleien" ItemHelp="" MinExpression="" MaxExpression="" ExcludeFromText="0" ExcludeCaption="0" Visibility="1" CarryForward="0" Optional="1">
          <Answer AnswerId="22894" OrderNumber="1" OptionText="Ja" VerboseText="Følges opp av hjemmesykepleien." ShortCode="J"/>
          <Answer AnswerId="22895" OrderNumber="2" OptionText="Nei*" ShortCode="N"/>
        </FormItem>
      </Item>
    </Page>
    <Page PageTitle="Stell hjemme*">
      <Item ItemId="4633" ItemType="2" VarName="FOOT_HOMECARE" LoincScale="ORD" DisplayFormat="">
        <FormItem ItemText="Stelles av" ItemHelp="" MinExpression="" MaxExpression="" ExcludeFromText="0" ExcludeCaption="0" Visibility="1" CarryForward="0" Optional="1">
          <Answer AnswerId="25100" OrderNumber="1" OptionText="pasienten selv."/>
          <Answer AnswerId="25101" OrderNumber="2" OptionText="pårørende."/>
        </FormItem>
      </Item>
    </Page>
    <Page PageTitle="Hjemmesykepleie">
      <Item ItemId="4391" ItemType="4" VarName="SONE_HJEMMESPL" LoincScale="NAR" DisplayFormat="" Multiline="0">
        <FormItem ItemText="Sone" ItemHelp="Sone for hjemmesykepleien" MinExpression="" MaxExpression="" ExcludeFromText="0" ExcludeCaption="0" Visibility="1" CarryForward="1" Optional="1">
          <Answer/>
        </FormItem>
      </Item>
      <Item ItemId="4632" ItemType="4" VarName="TLF_HJEMMESPL" LoincScale="NAR" DisplayFormat="" Multiline="0">
        <FormItem ItemText="Telefon" ItemHelp="Telefonnummer til hjemmesykepleien" MinExpression="" MaxExpression="" ExcludeFromText="0" ExcludeCaption="0" Visibility="1" CarryForward="1" Optional="1">
          <Answer/>
        </FormItem>
      </Item>
    </Page>
  </Form>
  <Actions>
    <PageAction MasterId="3248">
      <Activate EnumVal="1" PageConditionId="1946" PageNumber="2" ComparisonType="6" ComparisonDescription="Not Equal"/>
    </PageAction>
    <PageAction MasterId="3249">
      <Activate EnumVal="2" PageConditionId="1933" PageNumber="7" ComparisonType="1" ComparisonDescription="Equal to"/>
      <Activate EnumVal="3" PageConditionId="1934" PageNumber="7" ComparisonType="1" ComparisonDescription="Equal to"/>
      <Activate EnumVal="4" PageConditionId="1935" PageNumber="7" ComparisonType="1" ComparisonDescription="Equal to"/>
    </PageAction>
    <PageAction MasterId="6392">
      <Activate EnumVal="1" PageConditionId="1948" PageNumber="9" ComparisonType="1" ComparisonDescription="Equal to"/>
    </PageAction>
    <PageAction MasterId="3218">
      <Activate EnumVal="2" PageConditionId="1936" PageNumber="11" ComparisonType="1" ComparisonDescription="Equal to"/>
      <Activate EnumVal="3" PageConditionId="1937" PageNumber="11" ComparisonType="1" ComparisonDescription="Equal to"/>
    </PageAction>
    <PageAction MasterId="4282">
      <Activate EnumVal="1" PageConditionId="1942" PageNumber="13" ComparisonType="1" ComparisonDescription="Equal to"/>
    </PageAction>
    <PageAction MasterId="10316">
      <Activate EnumVal="1" PageConditionId="5542" PageNumber="14" ComparisonType="5" ComparisonDescription="Greater than or equal to"/>
    </PageAction>
    <PageAction MasterId="4281">
      <Activate EnumVal="1" PageConditionId="1938" PageNumber="15" ComparisonType="1" ComparisonDescription="Equal to"/>
    </PageAction>
    <PageAction MasterId="4290">
      <Activate EnumVal="3" PageConditionId="1940" PageNumber="16" ComparisonType="1" ComparisonDescription="Equal to"/>
    </PageAction>
    <PageAction MasterId="10316">
      <Activate EnumVal="1" PageConditionId="5545" PageNumber="17" ComparisonType="5" ComparisonDescription="Greater than or equal to"/>
      <Activate EnumVal="2" PageConditionId="5543" PageNumber="18" ComparisonType="5" ComparisonDescription="Greater than or equal to"/>
      <Activate EnumVal="3" PageConditionId="5544" PageNumber="19" ComparisonType="5" ComparisonDescription="Greater than or equal to"/>
    </PageAction>
    <PageAction MasterId="4629">
      <Activate EnumVal="1" PageConditionId="1943" PageNumber="21" ComparisonType="1" ComparisonDescription="Equal to"/>
    </PageAction>
    <PageAction MasterId="4267">
      <Activate EnumVal="2" PageConditionId="1944" PageNumber="24" ComparisonType="1" ComparisonDescription="Equal to"/>
      <Activate EnumVal="1" PageConditionId="1945" PageNumber="25" ComparisonType="1" ComparisonDescription="Equal to"/>
    </PageAction>
  </Actions>
</StudyForm>
