<?xml version="1.0" encoding="ISO-8859-1"?>
<StudyForm>
  <Form FormId="298" FormName="DIAPOL_PAID" FormTitle="PAID - Diabetesrelaterte problemområder" Instructions="De neste utsagnene handler om vanlige diabetesrelaterte utfordringer.  Hvilke av de følgende forhold er for tiden et problem for deg?">
    <Page PageTitle="PAID - Diabetesrelaterte problemområder" PageIntroduction="Er følgende for tiden et problem for deg?">
      <Item ItemId="3960" ItemType="2" VarName="PAID_01" LoincScale="ORD" DisplayFormat="Vertical">
        <FormItem ItemText="Har ikke klare og konkrete mål for diabetesomsorgen min" ItemHelp="" MinExpression="" MaxExpression="" ExcludeFromText="0" ExcludeCaption="0" Visibility="1" CarryForward="0" Optional="0">
          <Answer AnswerId="20471" OrderNumber="1" OptionText="Ikke et problem" Score="0.00"/>
          <Answer AnswerId="20472" OrderNumber="2" OptionText="Mindre problem" Score="1.00"/>
          <Answer AnswerId="20473" OrderNumber="3" OptionText="Middels problem" Score="2.00"/>
          <Answer AnswerId="20474" OrderNumber="4" OptionText="Nokså alvorlig problem" Score="3.00"/>
          <Answer AnswerId="20475" OrderNumber="5" OptionText="Alvorlig problem" Score="4.00"/>
        </FormItem>
      </Item>
      <Item ItemId="3961" ItemType="2" VarName="PAID_02" LoincScale="ORD" DisplayFormat="Vertical">
        <FormItem ItemText="Behandlingsopplegget for min diabetes gjør meg motløs" ItemHelp="" ExcludeFromText="0" ExcludeCaption="0" Visibility="1" CarryForward="0" ReadOnly="0" Optional="0">
          <Answer AnswerId="20476" OrderNumber="1" OptionText="Ikke et problem" Score="0.00"/>
          <Answer AnswerId="20477" OrderNumber="2" OptionText="Mindre problem" Score="1.00"/>
          <Answer AnswerId="20478" OrderNumber="3" OptionText="Middels problem" Score="2.00"/>
          <Answer AnswerId="20479" OrderNumber="4" OptionText="Nokså alvorlig problem" Score="3.00"/>
          <Answer AnswerId="20480" OrderNumber="5" OptionText="Alvorlig problem" Score="4.00"/>
        </FormItem>
      </Item>
      <Item ItemId="3962" ItemType="2" VarName="PAID_03" LoincScale="ORD" DisplayFormat="Vertical">
        <FormItem ItemText="Føler meg engstelig når jeg tenker på at jeg må leve med diabetes" ItemHelp="" MinExpression="" MaxExpression="" ExcludeFromText="0" ExcludeCaption="0" Visibility="1" CarryForward="0" Optional="0">
          <Answer AnswerId="20486" OrderNumber="1" OptionText="Ikke et problem" Score="0.00"/>
          <Answer AnswerId="20487" OrderNumber="2" OptionText="Mindre problem" Score="1.00"/>
          <Answer AnswerId="20488" OrderNumber="3" OptionText="Middels problem" Score="2.00"/>
          <Answer AnswerId="20489" OrderNumber="4" OptionText="Nokså alvorlig problem" Score="3.00"/>
          <Answer AnswerId="20490" OrderNumber="5" OptionText="Alvorlig problem" Score="4.00"/>
        </FormItem>
      </Item>
      <Item ItemId="3963" ItemType="2" VarName="PAID_04" LoincScale="ORD" DisplayFormat="Vertical">
        <FormItem ItemText="Opplever ubehagelige sosiale situasjoner knyttet til min diabetesomsorg" ItemHelp="F.eks. folk som forteller meg hva jeg bør spise" MinExpression="" MaxExpression="" ExcludeFromText="0" ExcludeCaption="0" Visibility="1" CarryForward="0" Optional="0">
          <Answer AnswerId="20496" OrderNumber="1" OptionText="Ikke et problem" Score="0.00"/>
          <Answer AnswerId="20497" OrderNumber="2" OptionText="Mindre problem" Score="1.00"/>
          <Answer AnswerId="20498" OrderNumber="3" OptionText="Middels problem" Score="2.00"/>
          <Answer AnswerId="20499" OrderNumber="4" OptionText="Nokså alvorlig problem" Score="3.00"/>
          <Answer AnswerId="20500" OrderNumber="5" OptionText="Alvorlig problem" Score="4.00"/>
        </FormItem>
      </Item>
      <Item ItemId="3964" ItemType="2" VarName="PAID_05" LoincScale="ORD" DisplayFormat="Vertical">
        <FormItem ItemText="Føler forsakelse og tap i forhold til mat og måltider" ItemHelp="" ExcludeFromText="0" ExcludeCaption="0" Visibility="1" CarryForward="0" ReadOnly="0" Optional="0">
          <Answer AnswerId="20506" OrderNumber="1" OptionText="Ikke et problem" Score="0.00"/>
          <Answer AnswerId="20507" OrderNumber="2" OptionText="Mindre problem" Score="1.00"/>
          <Answer AnswerId="20508" OrderNumber="3" OptionText="Middels problem" Score="2.00"/>
          <Answer AnswerId="20509" OrderNumber="4" OptionText="Nokså alvorlig problem" Score="3.00"/>
          <Answer AnswerId="20510" OrderNumber="5" OptionText="Alvorlig problem" Score="4.00"/>
        </FormItem>
      </Item>
      <Item ItemId="3965" ItemType="2" VarName="PAID_06" LoincScale="ORD" DisplayFormat="Vertical">
        <FormItem ItemText="Føler meg deprimert når jeg tenker på at jeg må leve med diabetes" ItemHelp="" MinExpression="" MaxExpression="" ExcludeFromText="0" ExcludeCaption="0" Visibility="1" CarryForward="0" Optional="0">
          <Answer AnswerId="20521" OrderNumber="1" OptionText="Ikke et problem" Score="0.00"/>
          <Answer AnswerId="20522" OrderNumber="2" OptionText="Mindre problem" Score="1.00"/>
          <Answer AnswerId="20523" OrderNumber="3" OptionText="Middels problem" Score="2.00"/>
          <Answer AnswerId="20524" OrderNumber="4" OptionText="Nokså alvorlig problem" Score="3.00"/>
          <Answer AnswerId="20525" OrderNumber="5" OptionText="Alvorlig problem" Score="4.00"/>
        </FormItem>
      </Item>
      <Item ItemId="3966" ItemType="2" VarName="PAID_07" LoincScale="ORD" DisplayFormat="Vertical">
        <FormItem ItemText="Vet ikke om humøret eller følelsene mine er knyttet til diabetes" ItemHelp="" MinExpression="" MaxExpression="" ExcludeFromText="0" ExcludeCaption="0" Visibility="1" CarryForward="0" Optional="0">
          <Answer AnswerId="20531" OrderNumber="1" OptionText="Ikke et problem" Score="0.00"/>
          <Answer AnswerId="20532" OrderNumber="2" OptionText="Mindre problem" Score="1.00"/>
          <Answer AnswerId="20533" OrderNumber="3" OptionText="Middels problem" Score="2.00"/>
          <Answer AnswerId="20534" OrderNumber="4" OptionText="Nokså alvorlig problem" Score="3.00"/>
          <Answer AnswerId="20535" OrderNumber="5" OptionText="Alvorlig problem" Score="4.00"/>
        </FormItem>
      </Item>
      <Item ItemId="3967" ItemType="2" VarName="PAID_08" LoincScale="ORD" DisplayFormat="">
        <FormItem ItemText="Føler meg overveldet av diabetessykdommen" ItemHelp="" MinExpression="" MaxExpression="" ExcludeFromText="0" ExcludeCaption="0" Visibility="1" CarryForward="0" Optional="0">
          <Answer AnswerId="20541" OrderNumber="1" OptionText="Ikke et problem" Score="0.00"/>
          <Answer AnswerId="20542" OrderNumber="2" OptionText="Mindre problem" Score="1.00"/>
          <Answer AnswerId="20543" OrderNumber="3" OptionText="Middels problem" Score="2.00"/>
          <Answer AnswerId="20544" OrderNumber="4" OptionText="Nokså alvorlig problem" Score="3.00"/>
          <Answer AnswerId="20545" OrderNumber="5" OptionText="Alvorlig problem" Score="4.00"/>
        </FormItem>
      </Item>
      <Item ItemId="3968" ItemType="2" VarName="PAID_09" LoincScale="ORD" DisplayFormat="">
        <FormItem ItemText="Bekymrer meg for å få føling" ItemHelp="" ExcludeFromText="0" ExcludeCaption="0" Visibility="1" CarryForward="0" ReadOnly="0" Optional="0">
          <Answer AnswerId="20551" OrderNumber="1" OptionText="Ikke et problem" Score="0.00"/>
          <Answer AnswerId="20552" OrderNumber="2" OptionText="Mindre problem" Score="1.00"/>
          <Answer AnswerId="20553" OrderNumber="3" OptionText="Middels problem" Score="2.00"/>
          <Answer AnswerId="20554" OrderNumber="4" OptionText="Nokså alvorlig problem" Score="3.00"/>
          <Answer AnswerId="20555" OrderNumber="5" OptionText="Alvorlig problem" Score="4.00"/>
        </FormItem>
      </Item>
      <Item ItemId="3969" ItemType="2" VarName="PAID_10" LoincScale="ORD" DisplayFormat="">
        <FormItem ItemText="Føler sinne når jeg tenker på at jeg må leve med diabetes" ItemHelp="" ExcludeFromText="0" ExcludeCaption="0" Visibility="1" CarryForward="0" ReadOnly="0" Optional="0">
          <Answer AnswerId="20561" OrderNumber="1" OptionText="Ikke et problem" Score="0.00"/>
          <Answer AnswerId="20562" OrderNumber="2" OptionText="Mindre problem" Score="1.00"/>
          <Answer AnswerId="20563" OrderNumber="3" OptionText="Middels problem" Score="2.00"/>
          <Answer AnswerId="20564" OrderNumber="4" OptionText="Nokså alvorlig problem" Score="3.00"/>
          <Answer AnswerId="20565" OrderNumber="5" OptionText="Alvorlig problem" Score="4.00"/>
        </FormItem>
      </Item>
      <Item ItemId="3970" ItemType="2" VarName="PAID_11" LoincScale="ORD" DisplayFormat="Vertical">
        <FormItem ItemText="Føler meg konstant opptatt av mat og spising" ItemHelp="" ExcludeFromText="0" ExcludeCaption="0" Visibility="1" CarryForward="0" ReadOnly="0" Optional="0">
          <Answer AnswerId="20571" OrderNumber="1" OptionText="Ikke et problem" Score="0.00"/>
          <Answer AnswerId="20572" OrderNumber="2" OptionText="Mindre problem" Score="1.00"/>
          <Answer AnswerId="20573" OrderNumber="3" OptionText="Middels problem" Score="2.00"/>
          <Answer AnswerId="20574" OrderNumber="4" OptionText="Nokså alvorlig problem" Score="3.00"/>
          <Answer AnswerId="20575" OrderNumber="5" OptionText="Alvorlig problem" Score="4.00"/>
        </FormItem>
      </Item>
      <Item ItemId="3971" ItemType="2" VarName="PAID_12" LoincScale="ORD" DisplayFormat="">
        <FormItem ItemText="Bekymrer meg for fremtiden og sjansen for alvorlige komplikasjoner" ItemHelp="" ExcludeFromText="0" ExcludeCaption="0" Visibility="1" CarryForward="0" ReadOnly="0" Optional="0">
          <Answer AnswerId="20581" OrderNumber="1" OptionText="Ikke et problem" Score="0.00"/>
          <Answer AnswerId="20582" OrderNumber="2" OptionText="Mindre problem" Score="1.00"/>
          <Answer AnswerId="20583" OrderNumber="3" OptionText="Middels problem" Score="2.00"/>
          <Answer AnswerId="20584" OrderNumber="4" OptionText="Nokså alvorlig problem" Score="3.00"/>
          <Answer AnswerId="20585" OrderNumber="5" OptionText="Alvorlig problem" Score="4.00"/>
        </FormItem>
      </Item>
      <Item ItemId="3972" ItemType="2" VarName="PAID_13" LoincScale="ORD" DisplayFormat="">
        <FormItem ItemText="Føler skyld og/eller engstelse når jeg kommer ut av rytme i håndteringen av min diabetes" ItemHelp="" ExcludeFromText="0" ExcludeCaption="0" Visibility="1" CarryForward="0" ReadOnly="0" Optional="0">
          <Answer AnswerId="20591" OrderNumber="1" OptionText="Ikke et problem" Score="0.00"/>
          <Answer AnswerId="20592" OrderNumber="2" OptionText="Mindre problem" Score="1.00"/>
          <Answer AnswerId="20593" OrderNumber="3" OptionText="Middels problem" Score="2.00"/>
          <Answer AnswerId="20594" OrderNumber="4" OptionText="Nokså alvorlig problem" Score="3.00"/>
          <Answer AnswerId="20595" OrderNumber="5" OptionText="Alvorlig problem" Score="4.00"/>
        </FormItem>
      </Item>
      <Item ItemId="3973" ItemType="2" VarName="PAID_14" LoincScale="ORD" DisplayFormat="">
        <FormItem ItemText="&quot;Aksepterer&quot; ikke at jeg har diabetes" ItemHelp="" ExcludeFromText="0" ExcludeCaption="0" Visibility="1" CarryForward="0" ReadOnly="0" Optional="0">
          <Answer AnswerId="20601" OrderNumber="1" OptionText="Ikke et problem" Score="0.00"/>
          <Answer AnswerId="20602" OrderNumber="2" OptionText="Mindre problem" Score="1.00"/>
          <Answer AnswerId="20603" OrderNumber="3" OptionText="Middels problem" Score="2.00"/>
          <Answer AnswerId="20604" OrderNumber="4" OptionText="Nokså alvorlig problem" Score="3.00"/>
          <Answer AnswerId="20605" OrderNumber="5" OptionText="Alvorlig problem" Score="4.00"/>
        </FormItem>
      </Item>
      <Item ItemId="3974" ItemType="2" VarName="PAID_15" LoincScale="ORD" DisplayFormat="">
        <FormItem ItemText="Føler meg misfornøyd med diabeteslegen min" ItemHelp="" ExcludeFromText="0" ExcludeCaption="0" Visibility="1" CarryForward="0" ReadOnly="0" Optional="0">
          <Answer AnswerId="20611" OrderNumber="1" OptionText="Ikke et problem" Score="0.00"/>
          <Answer AnswerId="20612" OrderNumber="2" OptionText="Mindre problem" Score="1.00"/>
          <Answer AnswerId="20613" OrderNumber="3" OptionText="Middels problem" Score="2.00"/>
          <Answer AnswerId="20614" OrderNumber="4" OptionText="Nokså alvorlig problem" Score="3.00"/>
          <Answer AnswerId="20615" OrderNumber="5" OptionText="Alvorlig problem" Score="4.00"/>
        </FormItem>
      </Item>
      <Item ItemId="3975" ItemType="2" VarName="PAID_16" LoincScale="ORD" DisplayFormat="">
        <FormItem ItemText="Føler at diabetes tar for mye av min fysiske og psykiske energi i det daglige" ItemHelp="" ExcludeFromText="0" ExcludeCaption="0" Visibility="1" CarryForward="0" ReadOnly="0" Optional="0">
          <Answer AnswerId="20626" OrderNumber="1" OptionText="Ikke et problem" Score="0.00"/>
          <Answer AnswerId="20627" OrderNumber="2" OptionText="Mindre problem" Score="1.00"/>
          <Answer AnswerId="20628" OrderNumber="3" OptionText="Middels problem" Score="2.00"/>
          <Answer AnswerId="20629" OrderNumber="4" OptionText="Nokså alvorlig problem" Score="3.00"/>
          <Answer AnswerId="20630" OrderNumber="5" OptionText="Alvorlig problem" Score="4.00"/>
        </FormItem>
      </Item>
      <Item ItemId="3976" ItemType="2" VarName="PAID_17" LoincScale="ORD" DisplayFormat="">
        <FormItem ItemText="Føler meg alene med min diabetes" ItemHelp="" ExcludeFromText="0" ExcludeCaption="0" Visibility="1" CarryForward="0" ReadOnly="0" Optional="0">
          <Answer AnswerId="20636" OrderNumber="1" OptionText="Ikke et problem" Score="0.00"/>
          <Answer AnswerId="20637" OrderNumber="2" OptionText="Mindre problem" Score="1.00"/>
          <Answer AnswerId="20638" OrderNumber="3" OptionText="Middels problem" Score="2.00"/>
          <Answer AnswerId="20639" OrderNumber="4" OptionText="Nokså alvorlig problem" Score="3.00"/>
          <Answer AnswerId="20640" OrderNumber="5" OptionText="Alvorlig problem" Score="4.00"/>
        </FormItem>
      </Item>
      <Item ItemId="3977" ItemType="2" VarName="PAID_18" LoincScale="ORD" DisplayFormat="">
        <FormItem ItemText="Føler at familie og venner ikke støtter meg i mine anstrengelser for å håndtere min diabetes" ItemHelp="" ExcludeFromText="0" ExcludeCaption="0" Visibility="1" CarryForward="0" ReadOnly="0" Optional="0">
          <Answer AnswerId="20646" OrderNumber="1" OptionText="Ikke et problem" Score="0.00"/>
          <Answer AnswerId="20647" OrderNumber="2" OptionText="Mindre problem" Score="1.00"/>
          <Answer AnswerId="20648" OrderNumber="3" OptionText="Middels problem" Score="2.00"/>
          <Answer AnswerId="20649" OrderNumber="4" OptionText="Nokså alvorlig problem" Score="3.00"/>
          <Answer AnswerId="20650" OrderNumber="5" OptionText="Alvorlig problem" Score="4.00"/>
        </FormItem>
      </Item>
      <Item ItemId="3978" ItemType="2" VarName="PAID_19" LoincScale="ORD" DisplayFormat="">
        <FormItem ItemText="Å mestre komplikasjoner til min diabetes" ItemHelp="" ExcludeFromText="0" ExcludeCaption="0" Visibility="1" CarryForward="0" ReadOnly="0" Optional="0">
          <Answer AnswerId="20656" OrderNumber="1" OptionText="Ikke et problem" Score="0.00"/>
          <Answer AnswerId="20657" OrderNumber="2" OptionText="Mindre problem" Score="1.00"/>
          <Answer AnswerId="20658" OrderNumber="3" OptionText="Middels problem" Score="2.00"/>
          <Answer AnswerId="20659" OrderNumber="4" OptionText="Nokså alvorlig problem" Score="3.00"/>
          <Answer AnswerId="20660" OrderNumber="5" OptionText="Alvorlig problem" Score="4.00"/>
        </FormItem>
      </Item>
      <Item ItemId="3979" ItemType="2" VarName="PAID_20" LoincScale="ORD" DisplayFormat="">
        <FormItem ItemText="Føler meg &quot;utbrent&quot; av den konstante anstrengelsen diabeteshåndteringen krever" ItemHelp="" ExcludeFromText="0" ExcludeCaption="0" Visibility="1" CarryForward="0" ReadOnly="0" Optional="0">
          <Answer AnswerId="20666" OrderNumber="1" OptionText="Ikke et problem" Score="0.00"/>
          <Answer AnswerId="20667" OrderNumber="2" OptionText="Mindre problem" Score="1.00"/>
          <Answer AnswerId="20668" OrderNumber="3" OptionText="Middels problem" Score="2.00"/>
          <Answer AnswerId="20669" OrderNumber="4" OptionText="Nokså alvorlig problem" Score="3.00"/>
          <Answer AnswerId="20670" OrderNumber="5" OptionText="Alvorlig problem" Score="4.00"/>
        </FormItem>
      </Item>
    </Page>
    <Page PageTitle="Oppsummering">
      <Item ItemId="3980" ItemType="1" VarName="PAID_SUM" LoincScale="QN" UnitStr="poeng" DisplayFormat="">
        <FormItem ItemText="Sum PAID" ItemHelp="" Expression="PAID_01 + PAID_02 + PAID_03 + PAID_04 + PAID_05 + PAID_06 + PAID_07 + PAID_08 +PAID_09 + PAID_10 + PAID_11 + PAID_12 + PAID_13 + PAID_14 + PAID_15 + PAID_16 + PAID_17 + PAID_18 + PAID_19 + PAID_20 - 20" MinExpression="0" MaxExpression="80" ExcludeFromText="0" ExcludeCaption="0" Visibility="1" CarryForward="0" Optional="1">
          <Answer/>
        </FormItem>
      </Item>
    </Page>
  </Form>
  <Actions>
	</Actions>
</StudyForm>
