<?xml version="1.0" encoding="ISO-8859-1"?>
<StudyForm>
  <Form FormId="933" FormName="GbdPsykolog" FormTitle="Notat psykolog">
    <Page PageTitle="Auto*" PageIntroduction="This page was autogenerated">
      <Item ItemId="1791" ItemType="2" VarName="VAR1791" LoincScale="ORD">
        <FormItem ItemText="Type kontakt" ItemHelp="" ExcludeFromText="0" ExcludeCaption="0" Visibility="1" CarryForward="0" ReadOnly="0" Optional="1">
          <Answer AnswerId="10842" OrderNumber="1" OptionText="Direkte pasientbehandling"/>
          <Answer AnswerId="10843" OrderNumber="2" OptionText="Råd/veiledning til annet helsepersonell"/>
        </FormItem>
      </Item>
      <Item ItemId="1793" ItemType="2" VarName="VAR1793" LoincScale="ORD">
        <FormItem ItemText="Råd/veiledning til annet helsepersonell" ItemHelp="" ExcludeFromText="0" ExcludeCaption="0" Visibility="1" CarryForward="0" ReadOnly="0" Optional="1">
          <Answer AnswerId="10845" OrderNumber="1" OptionText="Råd/veiledning til lege"/>
          <Answer AnswerId="10846" OrderNumber="2" OptionText="Råd/veiledning til avdeling/gruppe"/>
        </FormItem>
      </Item>
    </Page>
  </Form>
  <Actions>
    <PageAction MasterId="1791">
      <Activate EnumVal="2" PageConditionId="6305" PageNumber="2" ComparisonType="1" ComparisonDescription="Equal to"/>
    </PageAction>
  </Actions>
</StudyForm>
